Workbook
Name \0: #REF!
Name \a: #REF!
Name \b: #REF!
Name \c: #REF!
Name \charles: #REF!
Name \d: #REF!
Name \f: #N/A
Name \g: #N/A
Name \H: #REF!
Name \i: #REF!
Name \J: #REF!
Name \K: #REF!
Name \L: #REF!
Name \m: #REF!
Name \N: #REF!
Name \p: #REF!
Name \Q: #REF!
Name \r: #REF!
Name \s: #REF!
Name \u: #REF!
Name \v: #N/A
Name \x: #N/A
Name \z: #REF!
Name ___________ari2: #REF!
Name ___________ari3: #REF!
Name ___________ari4: #REF!
Name ___________ari5: #REF!
Name ___________ari6: #REF!
Name ___________ari7: #REF!
Name ___________ari8: #REF!
Name ___________m10: #REF!
Name ___________m11: #REF!
Name ___________m2: #REF!
Name ___________m3: #REF!
Name ___________m4: #REF!
Name ___________m5: #REF!
Name ___________m6: #REF!
Name ___________m7: #REF!
Name ___________m8: #REF!
Name ___________m9: #REF!
Name __________R: #REF!
Name _________ari2: #REF!
Name _________ari3: #REF!
Name _________ari4: #REF!
Name _________ari5: #REF!
Name _________ari6: #REF!
Name _________ari7: #REF!
Name _________ari8: #REF!
Name _________m10: #REF!
Name _________m11: #REF!
Name _________m2: #REF!
Name _________m3: #REF!
Name _________m4: #REF!
Name _________m5: #REF!
Name _________m6: #REF!
Name _________m7: #REF!
Name _________m8: #REF!
Name _________m9: #REF!
Name _______ari2: #REF!
Name _______ari3: #REF!

Sheet Azzas 2154
B1: Azzas 2154
B2: Dados financeiros e operacionais
B3: Financial and operating data

Sheet Revenue per BU and channel
C2: Revenue per BU and channel
B4: Português | C4: English | D4: 1Q22 | E4: 2Q22 | F4: 3Q22 | G4: 4Q22 | H4: 1Q23 | I4: 2Q23 | J4: 3Q23 | K4: 4Q23 | L4: 1Q24 | M4: 2Q24 | N4: 3Q24 | O4: 4Q24 | P4: 1Q25 | Q4: 2Q25 | R4: 3Q25 | T4: CQGR | V4: 4Q25 | W4: 1Q26 | X4: 2Q26 | Y4: 3Q26 | Z4: 4Q26 | AA4: 1Q27 | AB4: 2Q27 | AC4: 3Q27 | AD4: 4Q27 | AE4: 1Q28 | AF4: 2Q28 | AG4: 3Q28 | AH4: 4Q28 | AI4: 1Q29 | AJ4: 2Q29 | AK4: 3Q25 | AL4: 4Q29 | AM4: 1Q30 | AN4: 2Q30 | AO4: 3Q30 | AP4: 4Q30 | AQ4: 1Q31 | AR4: 2Q31 | AS4: 3Q31 | AT4: 4Q31
B6: Receita por Businness Unit | C6: Revenue per Business Unit | D6: 2271.3 | E6: 2613.5 | F6: 2969.4 | G6: 3306.3 | H6: 2789.9 | I6: 3047.9 | J6: 3274.3 | K6: 3667.3 | L6: 2894.1 | M6: 3370.5 | N6: 3673.5 | O6: 4221.6 | P6: 3311.8 | Q6: 3620 | R6: 3716.2
B7: Operações Continuadas | C7: Continued Operations | D7: 2210.3 | E7: 2538.2 | F7: 2890.4 | G7: 3218.2 | H7: 2700 | I7: 2945.6 | J7: 3173.3 | K7: 3554.7 | L7: 2807.8 | M7: 3269.5 | N7: 3558.7 | O7: 4094.7 | P7: 3260.3 | Q7: 3606.2 | R7: 3714.7
B8: Shoes & Bags | C8: Shoes & Bags | D8: 813.7 | E8: 867.8 | F8: 1048.3 | G8: 1108.9 | H8: 943.4 | I8: 1002.9 | J8: 1153.9 | K8: 1215 | L8: 991 | M8: 1095.2 | N8: 1186 | O8: 1263.5 | P8: 1038.2 | Q8: 1103.3 | R8: 1119.2
B9: Fashion & Lifestyle Women | C9: Fashion & Lifestyle Women | D9: 706.4 | E9: 874.1 | F9: 963.6 | G9: 978.4 | H9: 915.9 | I9: 1028.6 | J9: 1053.4 | K9: 1088.9 | L9: 979.4 | M9: 1202.9 | N9: 1239.2 | O9: 1341.4 | P9: 1244.5 | Q9: 1444.9 | R9: 1465.3
B10: Fashion & Lifestyle Men | C10: Fashion & Lifestyle Men | D10: 203.4 | E10: 260.9 | F10: 312.6 | G10: 476.1 | H10: 294.7 | I10: 337 | J10: 374.1 | K10: 538.1 | L10: 320.3 | M10: 377.7 | N10: 466.3 | O10: 643.6 | P10: 360.7 | Q10: 421.3 | R10: 491.4
B11: Basic | C11: Basic | D11: 485.4 | E11: 534.8 | F11: 558.3 | G11: 661.3 | H11: 544 | I11: 574.4 | J11: 591.2 | K11: 712.3 | L11: 515.9 | M11: 593.4 | N11: 666.9 | O11: 844.1 | P11: 616.1 | Q11: 636.5 | R11: 638.8
B12: Outros | C12: Other | D12: 1.4 | E12: 0.6 | F12: 7.6 | G12: -6.5 | H12: 2 | I12: 2.7 | J12: 0.7 | K12: 0.4 | L12: 1.2 | M12: 0.3 | N12: 0.3 | O12: 2.1 | P12: 0.8 | Q12: 0.2 | R12: 0
B13: Operações Descontinuadas | C13: Discontinued Operations | D13: 61 | E13: 75.3 | F13: 79 | G13: 88.1 | H13: 89.9 | I13: 102.3 | J13: 101 | K13: 112.6 | L13: 86.3 | M13: 101 | N13: 114.8 | O13: 126.9 | P13: 51.5 | Q13: 13.8 | R13: 1.5
B15: Receita por Canal | C15: Revenue per Channel | D15: 2271.3 | E15: 2613.5 | F15: 2969.4 | G15: 3306.3 | H15: 2789.9 | I15: 3047.9 | J15: 3274.3 | K15: 3667.3 | L15: 2894.1 | M15: 3370.5 | N15: 3673.5 | O15: 4221.6 | P15: 3311.8 | Q15: 3620 | R15: 3716.2
B16: Operações Continuadas | C16: Continued Operations | D16: 2210.3 | E16: 2538.2 | F16: 2890.4 | G16: 3218.2 | H16: 2700 | I16: 2945.6 | J16: 3173.3 | K16: 3554.7 | L16: 2807.8 | M16: 3269.5 | N16: 3558.7 | O16: 4094.7 | P16: 3260.3 | Q16: 3606.2 | R16: 3714.7
B17: Sell-Out | C17: Sell-Out | D17: 1014.8 | E17: 1183.8 | F17: 1269.4 | G17: 1640.8 | H17: 1219 | I17: 1374.7 | J17: 1438.5 | K17: 1936.7 | L17: 1374.5 | M17: 1595.9 | N17: 1709.6 | O17: 2280.9 | P17: 1610.3 | Q17: 1781.3 | R17: 1816.3
B18: Lojas próprias | C18: Owned Stores | D18: 585.4 | E18: 751 | F18: 760.3 | G18: 1047.1 | H18: 731.2 | I18: 862.7 | J18: 857.9 | K18: 1190.9 | L18: 826.1 | M18: 985.6 | N18: 1012.3 | O18: 1419.4 | P18: 998.5 | Q18: 1129.9 | R18: 1082.5
... B28: Operações Continuadas | C28: Continued Operations | D28: 813.7 | E28: 867.8 | F28: 1048.3 | G28: 1108.9 | H28: 943.4 | I28: 1002.9 | J28: 1153.9 | K28: 1215 | L28: 991 | M28: 1095.2 | N28: 1186 | O28: 1263.5 | P28: 1038.2 | Q28: 1103.3 | R28: 1119.2
B29: Sell-Out | C29: Sell-Out | D29: 258.5 | E29: 315.1 | F29: 335.9 | G29: 384.5 | H29: 315.7 | I29: 361.5 | J29: 380.3 | K29: 455.9 | L29: 373.6 | M29: 414.1 | N29: 426.1 | O29: 493 | P29: 399.5 | Q29: 432.7 | R29: 420.2 | T29: =IFERROR(((R29/D29)^(1/15)-1),"N/A") -> 0.032919239 | V29: =R29*(1+T29) -> 434.03266
B30: Lojas próprias | C30: Owned Stores | D30: 88.8 | E30: 132.4 | F30: 120.2 | G30: 165.6 | H30: 125.5 | I30: 164.4 | J30: 148.1 | K30: 204.1 | L30: 142.4 | M30: 178.3 | N30: 176 | O30: 229.4 | P30: 160.9 | Q30: 187.4 | R30: 172.8
B31: E-commerce | C31: E-commerce | D31: 169.7 | E31: 182.7 | F31: 215.7 | G31: 218.9 | H31: 190.2 | I31: 197.1 | J31: 232.2 | K31: 251.8 | L31: 231.2 | M31: 235.8 | N31: 250.1 | O31: 263.6 | P31: 238.6 | Q31: 245.3 | R31: 247.4
B32: Sell-In | C32: Sell-In | D32: 430.1 | E32: 423.1 | F32: 570.4 | G32: 569.1 | H32: 521.8 | I32: 530.3 | J32: 639.7 | K32: 636.8 | L32: 520.9 | M32: 564.2 | N32: 627.2 | O32: 637.6 | P32: 515.7 | Q32: 556 | R32: 566.4 | T32: =IFERROR(((R32/D32)^(1/15)-1),"N/A") -> 0.018521623 | V32: =R32*(1+T32) -> 576.89065
B33: Franquia | C33: Franchises | D33: 237 | E33: 237.8 | F33: 288.4 | G33: 305.4 | H33: 275.3 | I33: 278 | J33: 313.4 | K33: 326.3 | L33: 268.4 | M33: 275.7 | N33: 305.3 | O33: 350.4 | P33: 260.6 | Q33: 267.4 | R33: 262
B34: Multimarcas | C34: Multibrand | D34: 193.1 | E34: 185.3 | F34: 282 | G34: 263.7 | H34: 246.5 | I34: 252.3 | J34: 326.3 | K34: 310.5 | L34: 252.5 | M34: 288.5 | N34: 321.9 | O34: 287.2 | P34: 255.1 | Q34: 288.6 | R34: 304.4
B35: Internacional | C35: International | D35: 119.9 | E35: 125.9 | F35: 137 | G35: 151 | H35: 104 | I35: 102.6 | J35: 123 | K35: 100.1 | L35: 86.3 | M35: 103.2 | N35: 120.2 | O35: 117 | P35: 111.5 | Q35: 99.5 | R35: 121.9 | T35: =IFERROR(((R35/D35)^(1/15)-1),"N/A") -> 0.0011034733 | V35: =R35*(1+T35) -> 122.03451
B36: Outros | C36: Other | D36: 5.2 | E36: 3.7 | F36: 5 | G36: 4.3 | H36: 1.9 | I36: 8.5 | J36: 10.9 | K36: 22.2 | L36: 10.2 | M36: 13.7 | N36: 12.5 | O36: 15.9 | P36: 11.5 | Q36: 15.1 | R36: 10.7 | T36: =IFERROR(((R36/D36)^(1/15)-1),"N/A") -> 0.049281532 | V36: =R36*(1+T36) -> 11.227312
B37: Operações Descontinuadas | C37: Discontinued Operations | D37: 17.3 | E37: 25.4 | F37: 30.5 | G37: 28.6 | H37: 29.9 | I37: 42.9 | J37: 33.3 | K37: 30.2 | L37: 20.5 | M37: 32.1 | N37: 30.4 | O37: 32.5 | P37: 1.2 | Q37: 1.6 | R37: -1.1
B39: Fashion Women | C39: Fashion Women | D39: 706.4 | E39: 874.1 | F39: 963.6 | G39: 978.4 | H39: 915.9 | I39: 1028.6 | J39: 1053.4 | K39: 1088.9 | L39: 979.4 | M39: 1202.9 | N39: 1239.2 | O39: 1341.4 | P39: 1244.5 | Q39: 1444.9 | R39: 1465.3
B40: Operações Continuadas | C40: Continued Operations | D40: 706.4 | E40: 874.1 | F40: 963.6 | G40: 978.4 | H40: 915.9 | I40: 1028.6 | J40: 1053.4 | K40: 1088.9 | L40: 979.4 | M40: 1202.9 | N40: 1239.2 | O40: 1341.4 | P40: 1244.5 | Q40: 1444.9 | R40: 1465.3
B41: Sell-Out | C41: Sell-Out | D41: 464.8 | E41: 516 | F41: 562.2 | G41: 667.1 | H41: 537.2 | I41: 584.2 | J41: 586 | K41: 733.2 | L41: 589.2 | M41: 680.5 | N41: 690 | O41: 893.8 | P41: 705.7 | Q41: 787.1 | R41: 785.4 | T41: =IFERROR(((R41/D41)^(1/15)-1),"N/A") -> 0.035591122 | V41: =R41*(1+T41) -> 813.35327
B42: Lojas próprias | C42: Owned Stores | D42: 309.1 | E42: 370.2 | F42: 388.3 | G42: 480.8 | H42: 377.6 | I42: 422.2 | J42: 410.5 | K42: 521 | L42: 429.4 | M42: 500 | N42: 493.1 | O42: 642.6 | P42: 528.8 | Q42: 580.4 | R42: 550.3
B43: E-commerce | C43: E-commerce | D43: 155.7 | E43: 145.8 | F43: 173.9 | G43: 186.3 | H43: 159.6 | I43: 162 | J43: 175.5 | K43: 212.2 | L43: 159.8 | M43: 180.5 | N43: 196.9 | O43: 251.2 | P43: 176.9 | Q43: 206.7 | R43: 235.1
B44: Sell-In | C44: Sell-In | D44: 147.1 | E44: 169.6 | F44: 225 | G44: 164.4 | H44: 210.6 | I44: 200.4 | J44: 263.7 | K44: 177.9 | L44: 185.7 | M44: 222.8 | N44: 269 | O44: 197.4 | P44: 289.1 | Q44: 245.7 | R44: 333.4 | T44: =IFERROR(((R44/D44)^(1/15)-1),"N/A") -> 0.056063894 | V44: =R44*(1+T44) -> 352.0917 | W44: =V44*(1+$T$44) -> 371.83133 | X44: =W44*(1+$T$44) -> 392.67765 | Y44: =X44*(1+$T$44) -> 414.69269 | Z44: =Y44*(1+$T$44) -> 437.94197 | AA44: =Z44*(1+$T$44) -> 462.4947 | AB44: =AA44*(1+$T$44) -> 488.42396 | AC44: =AB44*(1+$T$44) -> 515.80691 | AD44: =AC44*(1+$T$44) -> 544.72505 | ... AT44: =AS44*(1+$T$44) -> 1303.8285
B45: Franquia | C45: Franchises | D45: 3 | E45: 3 | F45: 4 | G45: 4.7 | H45: 3.8 | I45: 2.6 | J45: 4.3 | K45: 4.5 | L45: 2.5 | M45: 2.2 | N45: 2.9 | O45: 2.3 | P45: 1.8 | Q45: 2.4 | R45: 3.7
B46: Multimarcas | C46: Multibrand | D46: 144.1 | E46: 166.6 | F46: 221 | G46: 159.7 | H46: 206.8 | I46: 197.8 | J46: 259.4 | K46: 173.4 | L46: 183.2 | M46: 220.6 | N46: 266.1 | O46: 195.1 | P46: 287.3 | Q46: 243.3 | R46: 329.7
B47: Internacional | C47: International | D47: 93.6 | E47: 178.9 | F47: 161 | G47: 146 | H47: 165.7 | I47: 244.3 | J47: 194.8 | K47: 170.5 | L47: 203.1 | M47: 294.7 | N47: 260.4 | O47: 237.5 | P47: 236.9 | Q47: 398.8 | R47: 366.1 | T47: =IFERROR(((R47/D47)^(1/15)-1),"N/A") -> 0.095186946 | V47: =R47*(1+T47) -> 400.94794 | W47: =V47*(1+$T$47) -> 439.11295 | X47: =W47*(1+$T$47) -> 480.91077 | Y47: =X47*(1+$T$47) -> 526.6872 | Z47: =Y47*(1+$T$47) -> 576.82095 | AA47: =Z47*(1+$T$47) -> 631.72677 | AB47: =AA47*(1+$T$47) -> 691.85891 | AC47: =AB47*(1+$T$47) -> 757.71485 | AD47: =AC47*(1+$T$47) -> 829.83941 | ... AT47: =AS47*(1+$T$47) -> 3554.7265
B48: Outros | C48: Other | D48: 0.9 | E48: 9.6 | F48: 15.4 | G48: 0.9 | H48: 2.4 | I48: -0.3 | J48: 8.9 | K48: 7.3 | L48: 1.4 | M48: 4.9 | N48: 19.8 | O48: 12.7 | P48: 12.8 | Q48: 13.3 | R48: -19.6 | T48: =IFERROR(((R48/D48)^(1/15)-1),"N/A") -> -2.2280072 | V48: =-R48*(1+T48) -> -24.068941 | W48: =-V48*(1+$T$48) -> -29.556832 | X48: =-W48*(1+$T$48) -> -36.296001 | Y48: =-X48*(1+$T$48) -> -44.57175 | Z48: =-Y48*(1+$T$48) -> -54.734429 | AA48: =-Z48*(1+$T$48) -> -67.214272 | AB48: =-AA48*(1+$T$48) -> -82.539608 | AC48: =-AB48*(1+$T$48) -> -101.35923 | AD48: =-AC48*(1+$T$48) -> -124.46986 | ... AT48: =-AS48*(1+$T$48) -> -3328.7308
B49: Operações Descontinuadas | C49: Discontinued Operations | D49: 0 | E49: 0 | F49: 0 | G49: 0 | H49: 0 | I49: 0 | J49: 0 | K49: 0 | L49: 0 | M49: 0 | N49: 0 | O49: 0 | P49: 0 | Q49: 0 | R49: 0
B51: Fashion Men | C51: Fashion Men | D51: 214.6 | E51: 273.7 | F51: 321.8 | G51: 495.4 | H51: 308.7 | I51: 360.6 | J51: 402.5 | K51: 575.8 | L51: 343.3 | M51: 407.6 | N51: 504.6 | O51: 692.2 | P51: 388.1 | Q51: 430.5 | R51: 492.8
B52: Operações Continuadas | C52: Continued Operations | D52: 203.4 | E52: 260.9 | F52: 312.6 | G52: 476.1 | H52: 294.7 | I52: 337 | J52: 374.1 | K52: 538.1 | L52: 320.3 | M52: 377.7 | N52: 466.3 | O52: 643.6 | P52: 360.7 | Q52: 421.3 | R52: 491.4
B53: Sell-Out | C53: Sell-Out | D53: 144.8 | E53: 183.3 | F53: 204 | G53: 356.4 | H53: 198.2 | I53: 243.4 | J53: 269.3 | K53: 450.8 | L53: 225.5 | M53: 286.9 | N53: 331.3 | O53: 522.1 | P53: 257.8 | Q53: 302.7 | R53: 346.9 | T53: =IFERROR(((R53/D53)^(1/15)-1),"N/A") -> 0.059975228 | V53: =R53*(1+T53) -> 367.70541 | W53: =V53*(1+$T$53) -> 389.75862 | X53: =W53*(1+$T$53) -> 413.13448 | Y53: =X53*(1+$T$53) -> 437.91232 | Z53: =Y53*(1+$T$53) -> 464.17621 | AA53: =Z53*(1+$T$53) -> 492.01529 | AB53: =AA53*(1+$T$53) -> 521.52401 | AC53: =AB53*(1+$T$53) -> 552.80254 | AD53: =AC53*(1+$T$53) -> 585.95699 | ... AT53: =AS53*(1+$T$53) -> 1487.9804
B54: Lojas próprias | C54: Owned Stores | D54: 104.9 | E54: 139 | F54: 152.5 | G54: 241.9 | H54: 120.9 | I54: 156.8 | J54: 178.7 | K54: 264.7 | L54: 142.9 | M54: 182.8 | N54: 207.4 | O54: 324.7 | P54: 167.3 | Q54: 207.5 | R54: 224.2
B55: E-commerce | C55: E-commerce | D55: 39.9 | E55: 44.3 | F55: 51.5 | G55: 114.5 | H55: 77.3 | I55: 86.6 | J55: 90.6 | K55: 186.1 | L55: 82.6 | M55: 104.1 | N55: 123.9 | O55: 197.4 | P55: 90.5 | Q55: 95.2 | R55: 122.7
B56: Sell-In | C56: Sell-In | D56: 58.6 | E56: 77.6 | F56: 108.6 | G56: 119.6 | H56: 96.5 | I56: 93.5 | J56: 104.5 | K56: 87.1 | L56: 94 | M56: 90 | N56: 127.2 | O56: 121 | P56: 101 | Q56: 118.2 | R56: 141.6 | T56: =IFERROR(((R56/D56)^(1/15)-1),"N/A") -> 0.060582302 | V56: =R56*(1+T56) -> 150.17845 | W56: =V56*(1+$T$56) -> 159.27661 | X56: =W56*(1+$T$56) -> 168.92595 | Y56: =X56*(1+$T$56) -> 179.15988 | Z56: =Y56*(1+$T$56) -> 190.0138 | AA56: =Z56*(1+$T$56) -> 201.52527 | AB56: =AA56*(1+$T$56) -> 213.73413 | AC56: =AB56*(1+$T$56) -> 226.68264 | AD56: =AC56*(1+$T$56) -> 240.4156 | ... AT56: =AS56*(1+$T$56) -> 616.13042
B57: Franquia | C57: Franchises | D57: 15.8 | E57: 19.3 | F57: 29.6 | G57: 36 | H57: 22.7 | I57: 28.9 | J57: 29.7 | K57: 34.5 | L57: 32.1 | M57: 31.9 | N57: 40.3 | O57: 49.7 | P57: 32.9 | Q57: 39.8 | R57: 41.7
B58: Multimarcas | C58: Multibrand | D58: 42.8 | E58: 58.3 | F58: 79 | G58: 83.6 | H58: 73.8 | I58: 64.6 | J58: 74.8 | K58: 52.6 | L58: 61.9 | M58: 58.1 | N58: 86.9 | O58: 71.3 | P58: 68.1 | Q58: 78.4 | R58: 99.9
B59: Outros | C59: Other | D59: 0 | E59: 0 | F59: 0 | G59: 0.1 | H59: 0 | I59: 0.1 | J59: 0.3 | K59: 0.2 | L59: 0.8 | M59: 0.8 | N59: 7.8 | O59: 0.5 | P59: 1.9 | Q59: 0.4 | R59: 2.9 | T59: =IFERROR(((R59/D59)^(1/15)-1),"N/A") -> N/A
B60: Operações Descontinuadas | C60: Discontinued Operations | D60: 11.2 | E60: 12.8 | F60: 9.2 | G60: 19.3 | H60: 14 | I60: 23.6 | J60: 28.4 | K60: 37.7 | L60: 23 | M60: 29.9 | N60: 38.3 | O60: 48.6 | P60: 27.4 | Q60: 9.2 | R60: 1.4
B62: Basic | C62: Basic | D62: 517.9 | E62: 571.9 | F62: 597.6 | G62: 701.5 | H62: 590 | I62: 610.2 | J62: 630.5 | K62: 757 | L62: 558.7 | M62: 632.4 | N62: 713 | O62: 889.9 | P62: 639 | Q62: 639.5 | R62: 640
B63: Operações Continuadas | C63: Continued Operations | D63: 485.4 | E63: 534.8 | F63: 558.3 | G63: 661.3 | H63: 544 | I63: 574.4 | J63: 591.2 | K63: 712.3 | L63: 515.9 | M63: 593.4 | N63: 666.9 | O63: 844.1 | P63: 616.1 | Q63: 636.5 | R63: 638.8
B64: Sell-Out | C64: Sell-Out | D64: 146.7 | E64: 169.4 | F64: 167.3 | G64: 232.8 | H64: 167.9 | I64: 185.6 | J64: 202.9 | K64: 296.8 | L64: 186.2 | M64: 214.4 | N64: 262.2 | O64: 372 | P64: 247.3 | Q64: 258.8 | R64: 263.8 | T64: =IFERROR(((R64/D64)^(1/15)-1),"N/A") -> 0.039895371 | V64: =R64*(1+T64) -> 274.3244 | W64: =V64*(1+$T$64) -> 285.26867 | X64: =W64*(1+$T$64) -> 296.64957 | Y64: =X64*(1+$T$64) -> 308.48452 | Z64: =Y64*(1+$T$64) -> 320.79162 | AA64: =Z64*(1+$T$64) -> 333.58972 | AB64: =AA64*(1+$T$64) -> 346.89841 | AC64: =AB64*(1+$T$64) -> 360.73805 | AD64: =AC64*(1+$T$64) -> 375.12983 | ... AT64: =AS64*(1+$T$64) -> 701.48101
B65: Lojas próprias | C65: Owned Stores | D65: 82.6 | E65: 109.4 | F65: 99.3 | G65: 158.8 | H65: 107.2 | I65: 119.3 | J65: 120.6 | K65: 201.1 | L65: 111.4 | M65: 124.5 | N65: 135.8 | O65: 222.7 | P65: 141.5 | Q65: 154.6 | R65: 135.2
B66: E-commerce | C66: E-commerce | D66: 64.1 | E66: 60 | F66: 68 | G66: 74 | H66: 60.7 | I66: 66.3 | J66: 82.3 | K66: 95.7 | L66: 74.8 | M66: 89.9 | N66: 126.4 | O66: 149.3 | P66: 105.8 | Q66: 104.2 | R66: 128.6
B67: Sell-In | C67: Sell-In | D67: 332.7 | E67: 358.5 | F67: 384 | G67: 423.6 | H67: 370.4 | I67: 382.4 | J67: 383.2 | K67: 413 | L67: 327.2 | M67: 373 | N67: 397 | O67: 464.9 | P67: 364.8 | Q67: 373.6 | R67: 371.3 | T67: =IFERROR(((R67/D67)^(1/15)-1),"N/A") -> 0.0073447868 | V67: =R67*(1+T67) -> 374.02712 | W67: =V67*(1+$T$67) -> 376.77427 | X67: =W67*(1+$T$67) -> 379.5416 | Y67: =X67*(1+$T$67) -> 382.32925 | Z67: =Y67*(1+$T$67) -> 385.13737 | AA67: =Z67*(1+$T$67) -> 387.96613 | AB67: =AA67*(1+$T$67) -> 390.81565 | AC67: =AB67*(1+$T$67) -> 393.68611 | AD67: =AC67*(1+$T$67) -> 396.57765 | ... AT67: =AS67*(1+$T$67) -> 445.83949
B68: Franquia | C68: Franchises | D68: 155.1 | E68: 182.3 | F68: 193.7 | G68: 236.7 | H68: 159.3 | I68: 188 | J68: 203.7 | K68: 236.5 | L68: 156.5 | M68: 188.9 | N68: 220.2 | O68: 257.9 | P68: 170.6 | Q68: 174.1 | R68: 183.9
B69: Multimarcas | C69: Multibrand | D69: 177.6 | E69: 176.2 | F69: 190.3 | G69: 186.9 | H69: 211.1 | I69: 194.4 | J69: 179.5 | K69: 176.5 | L69: 170.7 | M69: 184.1 | N69: 176.8 | O69: 207 | P69: 194.2 | Q69: 199.5 | R69: 187.4
B70: Outros | C70: Other | D70: 6 | E70: 6.9 | F70: 7 | G70: 4.9 | H70: 5.7 | I70: 6.4 | J70: 5.1 | K70: 2.5 | L70: 2.5 | M70: 6 | N70: 7.7 | O70: 7.2 | P70: 4 | Q70: 4.1 | R70: 3.7 | T70: =IFERROR(((R70/D70)^(1/15)-1),"N/A") -> -0.031714641 | V70: =R70*(1+T70) -> 3.5826558 | W70: =V70*(1+$T$70) -> 3.4690332 | X70: =W70*(1+$T$70) -> 3.359014 | Y70: =X70*(1+$T$70) -> 3.2524841 | Z70: =Y70*(1+$T$70) -> 3.1493327 | AA70: =Z70*(1+$T$70) -> 3.0494528 | AB70: =AA70*(1+$T$70) -> 2.9527405 | AC70: =AB70*(1+$T$70) -> 2.8590954 | AD70: =AC70*(1+$T$70) -> 2.7684202 | ... AT70: =AS70*(1+$T$70) -> 1.6530495
B71: Operações Descontinuadas | C71: Discontinued Operations | D71: 32.5 | E71: 37.1 | F71: 39.3 | G71: 40.2 | H71: 46 | I71: 35.8 | J71: 39.3 | K71: 44.7 | L71: 42.8 | M71: 39 | N71: 46.1 | O71: 45.8 | P71: 22.9 | Q71: 3 | R71: 1.2
B73: Outros | C73: Other | D73: 1.4 | E73: 0.6 | F73: 7.6 | G73: -6.5 | H73: 2 | I73: 2.7 | J73: 0.7 | K73: 0.4 | L73: 1.2 | M73: 0.3 | N73: 0.3 | O73: 2.1 | P73: 0.8 | Q73: 0.2 | R73: 0 | T73: Gross Revenue | V73: =V70+V67+V64+V56+V53+V48+V47+V44+V41+V36+V35+V32+V29 -> 3856.3271 | W73: =W70+W67+W64+W56+W53+W48+W47+W44+W41+W36+W35+W32+W29 -> 1995.9347 | X73: =X70+X67+X64+X56+X53+X48+X47+X44+X41+X36+X35+X32+X29 -> 2098.903 | Y73: =Y70+Y67+Y64+Y56+Y53+Y48+Y47+Y44+Y41+Y36+Y35+Y32+Y29 -> 2207.9466 | Z73: =Z70+Z67+Z64+Z56+Z53+Z48+Z47+Z44+Z41+Z36+Z35+Z32+Z29 -> 2323.2968 | AA73: =AA70+AA67+AA64+AA56+AA53+AA48+AA47+AA44+AA41+AA36+AA35+AA32+AA29 -> 2445.1531 | AB73: =AB70+AB67+AB64+AB56+AB53+AB48+AB47+AB44+AB41+AB36+AB35+AB32+AB29 -> 2573.6682 | AC73: =AC70+AC67+AC64+AC56+AC53+AC48+AC47+AC44+AC41+AC36+AC35+AC32+AC29 -> 2708.931 | ... AT73: =AT70+AT67+AT64+AT56+AT53+AT48+AT47+AT44+AT41+AT36+AT35+AT32+AT29 -> 4782.9085

Sheet P&L Pro Forma
C2: P&L Pro Forma
B4: Português | C4: English | D4: 1Q22 | E4: 2Q22 | F4: 3Q22 | G4: 4Q22 | H4: 1Q23 | I4: 2Q23 | J4: 3Q23 | K4: 4Q23 | L4: 1Q24 | M4: 2Q24 | N4: 3Q24 | O4: 4Q24 | P4: 1Q25 | Q4: 2Q25 | R4: 3Q25
B5: Receita Bruta | C5: Gross Revenue | D5: 2271.3 | E5: 2613.5 | F5: 2969.5 | G5: 3306.3 | H5: 2789.9 | I5: 3047.9 | J5: 3274.3 | K5: 3667.3 | L5: 2894.1 | M5: 3370.5 | N5: 3673.5 | O5: 4221.7 | P5: 3311.8 | Q5: 3620 | R5: 3718.3
B6: Deduções | C6: Deductions | D6: -354.6 | E6: -402.7 | F6: -466.4 | G6: -557 | H6: -492 | I6: -551.2 | J6: -559.6 | K6: -666 | L6: -527 | M6: -601.2 | N6: -635.3 | O6: -817.8 | P6: -615.3 | Q6: -718.6 | R6: -760.1
B7: Receita Líquida | C7: Net Revenue | D7: 1916.7 | E7: 2210.8 | F7: 2503.1 | G7: 2749.3 | H7: 2297.9 | I7: 2496.7 | J7: 2714.7 | K7: 3001.3 | L7: 2367.1 | M7: 2769.3 | N7: 3038.2 | O7: 3403.9 | P7: 2696.5 | Q7: 2901.4 | R7: 2958.2
B8: Custo da Mercadoria Vendida (CMV) | C8: Cost of Goods Sold (COGS) | D8: -889.6 | E8: -951.9 | F8: -1132.9 | G8: -1292 | H8: -1057.9 | I8: -1119.6 | J8: -1226.7 | K8: -1365.3 | L8: -1081.2 | M8: -1216 | N8: -1386.7 | O8: -1575.4 | P8: -1219.7 | Q8: -1280.9 | R8: -1356.8
B9: CMV (ex. D&A) | C9: COGS (ex. D&A) | D9: -881.1 | E9: -943.2 | F9: -1123.9 | G9: -1282.6 | H9: -1048.9 | I9: -1110.5 | J9: -1217.7 | K9: -1356.3 | L9: -1071.6 | M9: -1206.3 | N9: -1376.5 | O9: -1564.1 | P9: -1209.2 | Q9: -1271.2 | R9: -1346.4
B10: CMV (ex. D&A ex. IFRS-16) | C10: COGS (ex. D&A ex. IFRS-16) | D10: -882.3 | E10: -944.4 | F10: -1125.1 | G10: -1283.7 | H10: -1050 | I10: -1111.6 | J10: -1218.9 | K10: -1357.2 | L10: -1072.9 | M10: -1207.6 | N10: -1377.8 | O10: -1565.4 | P10: -1210.5 | Q10: -1272.5 | R10: -1347.7
B11: Arrendamentos (Impacto IFRS-16) | C11: Leases (IFRS-16 Impact) | D11: 1.2 | E11: 1.2 | F11: 1.2 | G11: 1.1 | H11: 1.1 | I11: 1.1 | J11: 1.2 | K11: 0.9 | L11: 1.3 | M11: 1.3 | N11: 1.3 | O11: 1.3 | P11: 1.3 | Q11: 1.3 | R11: 1.3
B12: Depreciação e Amortização | C12: Depreciation and Amortization | D12: -8.5 | E12: -8.7 | F12: -9 | G12: -9.4 | H12: -9 | I12: -9.1 | J12: -9 | K12: -9 | L12: -9.6 | M12: -9.7 | N12: -10.2 | O12: -11.3 | P12: -10.5 | Q12: -9.7 | R12: -10.4
B13: Lucro Bruto | C13: Gross Profit | D13: 1027.1 | E13: 1258.9 | F13: 1370.2 | G13: 1457.3 | H13: 1240 | I13: 1377.1 | J13: 1488 | K13: 1636 | L13: 1285.9 | M13: 1553.3 | N13: 1651.5 | O13: 1828.5 | P13: 1476.8 | Q13: 1620.5 | R13: 1601.4
B14: Despesa Total | C14: Total Expenses | D14: -804.1 | E14: -965.4 | F14: -1059.4 | G14: -1175.3 | H14: -1040.3 | I14: -1092.6 | J14: -1166.5 | K14: -4248.3 | L14: -1096.9 | M14: -1271.6 | N14: -1277.2 | O14: -2041.9 | P14: -1200.7 | Q14: -1258.6 | R14: -1336.6
B15: Despesas | C15: Expenses | D15: -718.1 | E15: -874.3 | F15: -976.4 | G15: -1046.9 | H15: -932.3 | I15: -970.2 | J15: -1041.3 | K15: -1168.6 | L15: -967.7 | M15: -1136.3 | N15: -1130.5 | O15: -1885.8 | P15: -1048.6 | Q15: -1104.8 | R15: -1155.3
B16: Fixas | C16: Fixed | D16: -349 | E16: -384.8 | F16: -419.8 | G16: -449.6 | H16: -405 | I16: -401.6 | J16: -460.5 | K16: -453.6 | L16: -446.8 | M16: -503.1 | N16: -525.7 | O16: -632.6 | P16: -481.3 | Q16: -473.6 | R16: -435.4
... B35: Margem Líquida | C35: Net Margin | D35: 0.082 | E35: 0.115 | F35: 0.088 | G35: 0.073 | H35: 0.057 | I35: 0.082 | J35: 0.087 | K35: -0.569 | L35: 0.034 | M35: 0.038 | N35: 0.027 | O35: -0.02 | P35: 0.044 | Q35: 0.185 | R35: 0.056

Sheet P&L Accounting
C2: P&L Accounting
B4: Português | C4: English | D4: 1Q22 | E4: 2Q22 | F4: 3Q22 | G4: 4Q22 | H4: 1Q23 | I4: 2Q23 | J4: 3Q23 | K4: 4Q23 | L4: 1Q24 | M4: 2Q24 | N4: 3Q24 | O4: 4Q24 | P4: 1Q25 | Q4: 2Q25 | R4: 3Q25
B5: Receita Líquida | C5: Net operating revenue | D5: 839.576 | E5: 944.752 | F5: 1137.985 | G5: 1311.413 | H5: 1025.291 | I5: 1131.023 | J5: 1265.823 | K5: 1424.631 | L5: 1072.182 | M5: 1357.108 | N5: 2546.621 | O5: 3403.842 | P5: 2696.5 | Q5: 2901.4 | R5: 2958.2
B6: Custo da mercadoria vendida | C6: Cost of goods sold | D6: -390.836 | E6: -416.145 | F6: -536.683 | G6: -606.428 | H6: -488.467 | I6: -516.509 | J6: -585.097 | K6: -627.634 | L6: -505.325 | M6: -681.46 | N6: -1152.465 | O6: -1575.442 | P6: -1219.7 | Q6: -1280.9 | R6: -1356.8
B7: Lucro Bruto | C7: Gross profit | D7: 448.74 | E7: 528.607 | F7: 601.302 | G7: 704.985 | H7: 536.824 | I7: 614.514 | J7: 680.726 | K7: 796.997 | L7: 566.857 | M7: 675.648 | N7: 1394.156 | O7: 1828.4 | P7: 1476.8 | Q7: 1620.5 | R7: 1601.4
B8: Receitas (despesas) operacionais | C8: Operating income (expenses) | D8: -287.588 | E8: -405.685 | F8: -474.127 | G8: -566.105 | H8: -432 | I8: -489.046 | J8: -505.521 | K8: -643.71 | L8: -459.688 | M8: -542.317 | N8: -1037.62 | O8: -2041.797 | P8: -1200.747 | Q8: -1258.6 | R8: -1336.6
B9: Comerciais | C9: Selling expenses | D9: -289.081 | E9: -333.615 | F9: -394.178 | G9: -472.497 | H9: -347.5 | I9: -401.33 | J9: -428.176 | K9: -536.626 | L9: -372.3 | M9: -443.9 | N9: -945.3 | O9: -1080.044 | P9: -911.602 | Q9: -881.3 | R9: -1000.4
B10: Administrativas e gerais | C10: General and administrative expenses | D10: -73.816 | E10: -73.402 | F10: -78.85 | G10: -104.172 | H10: -82.774 | I10: -88.527 | J10: -107.158 | K10: -117.113 | L10: -92.5 | M10: -105.2 | N10: -264 | O10: -595.385 | P10: -325.086 | Q10: -386.8 | R10: -359.9
B11: Outras despesas líquidas | C11: Other expenses, net | D11: 75.309 | E11: 1.332 | F11: -1.099 | G11: 10.564 | H11: -1.726 | I11: 0.811 | J11: 29.813 | K11: 10.029 | L11: 5.1 | M11: 6.8 | N11: 171.6 | O11: -366.368 | P11: 36.041 | Q11: 9.5 | R11: 23.7
B12: EBIT | C12: EBIT | D12: 161.152 | E12: 122.922 | F12: 127.175 | G12: 138.88 | H12: 104.824 | I12: 125.468 | J12: 175.205 | K12: 153.287 | L12: 107.169 | M12: 133.331 | N12: 356.536 | O12: -213.397 | P12: 276.054 | Q12: 361.905 | R12: 264.8
B13: Resultado Financeiro | C13: Financial income | D13: -20.407 | E13: -6.655 | F13: -12.48 | G13: -37.716 | H13: -39.591 | I13: -43.674 | J13: -48.113 | K13: -51.465 | L13: -47.621 | M13: -44.138 | N13: -145.087 | O13: -156.851 | P13: -157.732 | Q13: -201.7 | R13: -208.7
B14: EBT | C14: EBT | D14: 140.745 | E14: 116.267 | F14: 114.695 | G14: 101.164 | H14: 65.233 | I14: 81.794 | J14: 127.092 | K14: 101.822 | L14: 59.548 | M14: 89.193 | N14: 211.449 | O14: -370.248 | P14: 118.422 | Q14: 160.152 | R14: 56.1
B15: IRPJ e CSLL | C15: Income tax and social contribution | D15: -43.46 | E15: 3.554 | F15: -15.846 | G15: 5.419 | H15: -1.848 | I15: 18.668 | J15: -13.434 | K15: 19.346 | L15: 12.014 | M15: 38.717 | N15: -4.471 | O15: 302.347 | P15: -0.596 | Q15: 377.502 | R15: 108.819
B16: Corrente | C16: Current | D16: -39.603 | E16: -11.137 | F16: -14.267 | G16: -16.391 | H16: -10.947 | I16: -8.835 | J16: -41.422 | K16: 6.704 | L16: -13.781 | M16: 5.299 | N16: -3.17 | O16: 77.229 | P16: -9.531 | Q16: -1.29 | R16: 20.566
... B18: Lucro (Prejuízo) | C18: Profit (Loss) | D18: 97.285 | E18: 119.821 | F18: 98.849 | G18: 106.583 | H18: 63.385 | I18: 100.462 | J18: 113.658 | K18: 121.168 | L18: 71.562 | M18: 127.91 | N18: 206.978 | O18: -67.901 | P18: 117.826 | Q18: 537.654 | R18: 164.919

Sheet CAPEX
C2: CAPEX
B4: Português | C4: English | D4: 1Q22 | E4: 2Q22 | F4: 3Q22 | G4: 4Q22 | H4: 1Q23 | I4: 2Q23 | J4: 3Q23 | K4: 4Q23 | L4: 1Q24 | M4: 2Q24 | N4: 3Q24 | O4: 4Q24 | P4: 1Q25 | Q4: 2Q25 | R4: 3Q25 | T4: CQGR | V4: Average | X4: 4Q25 | Y4: 1Q26 | Z4: 2Q26 | AA4: 3Q26 | AB4: 4Q26 | AC4: 1Q27 | AD4: 2Q27 | AE4: 3Q27 | AF4: 4Q27 | AG4: 1Q28 | AH4: 2Q28 | AI4: 3Q28 | AJ4: 4Q28 | AK4: 1Q29 | AL4: 2Q29 | AM4: 3Q25 | AN4: 4Q29 | AO4: 1Q30 | AP4: 2Q30 | AQ4: 3Q30 | AR4: 4Q30 | AS4: 1Q31 | AT4: 2Q31 | AU4: 3Q31 | AV4: 4Q31 | AX4: Average
B5: CAPEX total | C5: Total CAPEX | D5: 69.6 | E5: 113.4 | F5: 109.7 | G5: 150.3 | H5: 100.8 | I5: 129.1 | J5: 120.4 | K5: 152 | L5: 95.7 | M5: 124.4 | N5: 139.1 | O5: 195.2 | P5: 84.4 | Q5: 94.2 | R5: 109.1 | V5: =SUM(V6:V8) -> 119.16 | W5: =AVERAGE(D5:R5) -> 119.16 | X5: =SUM(X6:X8) -> 112.58686 | Y5: =SUM(Y6:Y8) -> 116.20587 | Z5: =SUM(Z6:Z8) -> 119.9624 | AA5: =SUM(AA6:AA8) -> 123.86207 | AB5: =SUM(AB6:AB8) -> 127.91072 | AC5: =SUM(AC6:AC8) -> 132.11447 | AD5: =SUM(AD6:AD8) -> 136.47969 | AE5: =SUM(AE6:AE8) -> 141.01302 | ... AV5: =SUM(AV6:AV8) -> 251.86519 | AX5: =SUM(AX6:AX8) -> 186.50588
B6: Corporativo | C6: Corporate | D6: 40.6 | E6: 52.9 | F6: 48.3 | G6: 79.7 | H6: 65.5 | I6: 77.2 | J6: 59.8 | K6: 70.4 | L6: 47.5 | M6: 61.6 | N6: 69.2 | O6: 73 | P6: 46.5 | Q6: 60.7 | R6: 59.9 | T6: =((R6/D6)^(1/15))-1 -> 0.026266264 | V6: =AVERAGE(D6:R6) -> 60.853333 | X6: =R6*(1+T6) -> 61.473349 | Y6: =X6*(1+$T$6) -> 63.088024 | Z6: =Y6*(1+$T$6) -> 64.745111 | AA6: =Z6*(1+$T$6) -> 66.445723 | AB6: =AA6*(1+$T$6) -> 68.191004 | AC6: =AB6*(1+$T$6) -> 69.982127 | AD6: =AC6*(1+$T$6) -> 71.820296 | AE6: =AD6*(1+$T$6) -> 73.706747 | AF6: =AE6*(1+$T$6) -> 75.642748 | ... AV6: =AU6*(1+$T$6) -> 114.53234 | AX6: =AVERAGE(AF6:AT6) -> 91.265999
B7: Lojas - expansão e reformas | C7: Stores - expansion and refurbishing | D7: 20.3 | E7: 44.2 | F7: 35.7 | G7: 53.1 | H7: 14.1 | I7: 46.8 | J7: 42.7 | K7: 59.5 | L7: 28.4 | M7: 43.1 | N7: 46.8 | O7: 92.5 | P7: 21.4 | Q7: 21.2 | R7: 40.6 | T7: =((R7/D7)^(1/15))-1 -> 0.047294123 | V7: =AVERAGE(D7:R7) -> 40.693333 | X7: =R7*(1+T7) -> 42.520141 | Y7: =X7*(1+$T$7) -> 44.531094 | Z7: =Y7*(1+$T$7) -> 46.637153 | AA7: =Z7*(1+$T$7) -> 48.842816 | AB7: =AA7*(1+$T$7) -> 51.152795 | AC7: =AB7*(1+$T$7) -> 53.572021 | AD7: =AC7*(1+$T$7) -> 56.105663 | AE7: =AD7*(1+$T$7) -> 58.759131 | AF7: =AE7*(1+$T$7) -> 61.538093 | ... AV7: =AU7*(1+$T$7) -> 128.89697 | AX7: =AVERAGE(AF7:AT7) -> 86.745229
B8: Outros | C8: Other | D8: 8.7 | E8: 16.3 | F8: 25.7 | G8: 17.5 | H8: 21.2 | I8: 5.1 | J8: 17.9 | K8: 22.1 | L8: 19.8 | M8: 19.7 | N8: 23.1 | O8: 29.7 | P8: 16.5 | Q8: 12.3 | R8: 8.6 | T8: =((R8/D8)^(1/15))-1 -> -0.00077042456 | V8: =AVERAGE(D8:R8) -> 17.613333 | X8: =R8*(1+T8) -> 8.5933743 | Y8: =X8*(1+$T$8) -> 8.5867538 | Z8: =Y8*(1+$T$8) -> 8.5801384 | AA8: =Z8*(1+$T$8) -> 8.573528 | AB8: =AA8*(1+$T$8) -> 8.5669228 | AC8: =AB8*(1+$T$8) -> 8.5603226 | AD8: =AC8*(1+$T$8) -> 8.5537275 | AE8: =AD8*(1+$T$8) -> 8.5471375 | AF8: =AE8*(1+$T$8) -> 8.5405526 | ... AV8: =AU8*(1+$T$8) -> 8.4358811 | AX8: =AVERAGE(AF8:AT8) -> 8.494647
C11: D&A | D11: ='P&L Adjusted Pro Forma'!D40-'P&L Adjusted Pro Forma'!D28 -> 79 | E11: ='P&L Adjusted Pro Forma'!E40-'P&L Adjusted Pro Forma'!E28 -> 84.3 | F11: ='P&L Adjusted Pro Forma'!F40-'P&L Adjusted Pro Forma'!F28 -> 94.4 | G11: ='P&L Adjusted Pro Forma'!G40-'P&L Adjusted Pro Forma'!G28 -> 119 | H11: ='P&L Adjusted Pro Forma'!H40-'P&L Adjusted Pro Forma'!H28 -> 106 | I11: ='P&L Adjusted Pro Forma'!I40-'P&L Adjusted Pro Forma'!I28 -> 120.5 | J11: ='P&L Adjusted Pro Forma'!J40-'P&L Adjusted Pro Forma'!J28 -> 124.5 | K11: ='P&L Adjusted Pro Forma'!K40-'P&L Adjusted Pro Forma'!K28 -> 125.6 | ... R11: ='P&L Adjusted Pro Forma'!R40-'P&L Adjusted Pro Forma'!R28 -> 156.7 | T11: =((R11/D11)^(1/15))-1 -> 0.04671744 | X11: =R11+V12 -> 162.25 | Y11: =X11+$V$12 -> 167.8 | Z11: =Y11+$V$12 -> 173.35 | AA11: =Z11+$V$12 -> 178.9 | AB11: =AA11+$V$12 -> 184.45 | AC11: =AB11+$V$12 -> 190 | AD11: =AC11+$V$12 -> 195.55 | AE11: =AD11+$V$12 -> 201.1 | AF11: =AE11+$V$12 -> 206.65 | ... AV11: =AU11+$V$12 -> 295.45
C12: Δ D&A | E12: =E11-D11 -> 5.3 | F12: =F11-E11 -> 10.1 | G12: =G11-F11 -> 24.6 | H12: =H11-G11 -> -13 | I12: =I11-H11 -> 14.5 | J12: =J11-I11 -> 4 | K12: =K11-J11 -> 1.1 | L12: =L11-K11 -> 0.4 | ... R12: =R11-Q11 -> 3.7888791 | T12: =((R12/E12)^(1/15))-1 -> -0.022127293 | V12: =AVERAGE(E12:R12) -> 5.55
C14: CAPEX | D14: 2026 | E14: 2027 | F14: 2028 | G14: 2029 | H14: 2030 | I14: 2031
D15: =SUM(Y5:AB5) -> 487.94106 | E15: =SUM(Z5:AC5) -> 503.84966 | F15: =SUM(AA5:AD5) -> 520.36695 | G15: =SUM(AB5:AE5) -> 537.51789 | H15: =SUM(AC5:AF5) -> 555.32857 | I15: =SUM(AD5:AG5) -> 573.82615
C19: D&A | D19: 2025 | E19: 2026 | F19: 2027 | G19: 2028 | H19: 2029 | I19: 2030 | J19: 2031
D20: =X11+R11+Q11+P11 -> 623.56112 | E20: =SUM(Y11:AB11) -> 704.5 | F20: =SUM(Z11:AC11) -> 726.7 | G20: =SUM(AA11:AD11) -> 748.9 | H20: =SUM(AB11:AE11) -> 771.1 | I20: =SUM(AC11:AF11) -> 793.3 | J20: =SUM(AD11:AG11) -> 815.5
C21: Δ D&A | E21: =E20-D20 -> 80.938879 | F21: =F20-E20 -> 22.2 | G21: =G20-F20 -> 22.2 | H21: =H20-G20 -> 22.2 | I21: =I20-H20 -> 22.2 | J21: =J20-I20 -> 22.2

Sheet Balance Sheet
C2: Balance Sheet
B4: Português | C4: English | D4: 1Q22 | E4: 2Q22 | F4: 3Q22 | G4: 4Q22 | H4: 1Q23 | I4: 2Q23 | J4: 3Q23 | K4: 4Q23 | L4: 1Q24 | M4: 2Q24 | N4: 3Q24 | O4: 4Q24 | P4: 1Q25 | Q4: 2Q25 | R4: 3Q25 | S4: 4Q25 | T4: 1Q26 | U4: 2Q26 | V4: 3Q26 | W4: 4Q26 | X4: 1Q27 | Y4: 2Q27 | Z4: 3Q27 | AA4: 4Q27 | AB4: 1Q28 | AC4: 2Q28 | AD4: 3Q28 | AE4: 4Q28 | AF4: 1Q29 | AG4: 2Q29 | AH4: 3Q25 | AI4: 4Q29 | AJ4: 1Q30 | AK4: 2Q30 | AL4: 3Q30 | AM4: 4Q30 | AN4: 1Q31 | AO4: 2Q31 | AP4: 3Q31 | AQ4: 4Q31
B6: Ativo | C6: Assets
B7: Ativo circulante | C7: Current assets | D7: 2109.4 | E7: 2192.9 | F7: 2291.8 | G7: 2383.4 | H7: 2691 | I7: 2690.5 | J7: 2683.9 | K7: 2915.1 | L7: 2676.6 | M7: 2843.9 | N7: 6607.9 | O7: 6831.7 | P7: 7051.6 | Q7: 6866 | R7: 6874.5
B8: Caixa e equivalentes de caixa | C8: Cash and cash equivalents | D8: 106.7 | E8: 81.7 | F8: 74.9 | G8: 28.8 | H8: 83.6 | I8: 73.5 | J8: 60.7 | K8: 73.3 | L8: 53 | M8: 53.9 | N8: 162.4 | O8: 181.2 | P8: 136 | Q8: 177.4 | R8: 174.9
B9: Aplicações financeiras | C9: Financial Investments | D9: 603.6 | E9: 633.6 | F9: 471.2 | G9: 447.6 | H9: 699.5 | I9: 608.6 | J9: 582.9 | K9: 676.4 | L9: 539.8 | M9: 508.8 | N9: 604 | O9: 593.4 | P9: 967.4 | Q9: 645.8 | R9: 560.6
B10: Contas a receber | C10: Trade accounts receivables | D10: 631.3 | E10: 613.7 | F10: 722 | G10: 867.6 | H10: 743 | I10: 781.5 | J10: 921.8 | K10: 1125.4 | L10: 902.6 | M10: 963.3 | N10: 2512.5 | O10: 2816.3 | P10: 2448.8 | Q10: 2596.9 | R10: 2577
B11: Estoques | C11: Inventory | D11: 556.7 | E11: 651.7 | F11: 755.1 | G11: 772.1 | H11: 842.5 | I11: 864.5 | J11: 866.8 | K11: 774.3 | L11: 920.2 | M11: 968.2 | N11: 2313.1 | O11: 2218.8 | P11: 2457 | Q11: 2474.5 | R11: 2480.7
B12: Instrumentos financeiros - derivativos | C12: Financial Instruments - Derivatives | D12: 0.5 | E12: 0 | F12: 0 | G12: 0 | H12: 0 | I12: 0 | J12: 0 | K12: 0 | L12: 1 | M12: 52.9 | N12: 29.7 | O12: 136 | P12: 53.4 | Q12: 27.6 | R12: 18.7
B13: Impostos a recuperar | C13: Taxes recoverable | D13: 127.4 | E13: 148.2 | F13: 169 | G13: 187.5 | H13: 203.2 | I13: 231.7 | J13: 145 | K13: 111.7 | L13: 145.3 | M13: 131.4 | N13: 326.8 | O13: 323.4 | P13: 331.7 | Q13: 331.3 | R13: 381.6
B14: IRPJ e CSLL a recuperar | C14: Recovarable Income Tax and Social Contribution | D14: 2.6 | E14: 13.6 | F14: 14.4 | G14: 13.7 | H14: 19.3 | I14: 25.3 | J14: 5 | K14: 17.9 | L14: 19 | M14: 34.5 | N14: 224.8 | O14: 197.6 | P14: 225.4 | Q14: 239.8 | R14: 298.7
B15: Outros créditos | C15: Other credits | D15: 80.6 | E15: 50.4 | F15: 85.2 | G15: 66.1 | H15: 99.9 | I15: 105.4 | J15: 101.7 | K15: 136.1 | L15: 95.7 | M15: 130.9 | N15: 434.6 | O15: 365 | P15: 431.9 | Q15: 372.7 | R15: 382.3
B16: Ativo não circulante | C16: Non-current assets | D16: 1914.8 | E16: 2001.5 | F16: 2144.6 | G16: 2275.9 | H16: 2440.9 | I16: 2744.6 | J16: 2950.7 | K16: 3060.9 | L16: 3046.9 | M16: 3158.9 | N16: 8298.4 | O16: 8421.9 | P16: 8291.5 | Q16: 8650.8 | R16: 8641.8
B17: Aplicações financeiras | C17: Financial Investments | D17: 0 | E17: 0 | F17: 0 | G17: 0 | H17: 0 | I17: 0 | J17: 0 | K17: 0 | L17: 0 | M17: 0 | N17: 8.4 | O17: 1 | P17: 7.3 | Q17: 1.1 | R17: 7.8
B18: Instrumentos financeiros - derivativos | C18: Financial Instruments - Derivatives | D18: 0 | E18: 0 | F18: 0 | G18: 0 | H18: 0 | I18: 80.7 | J18: 77.5 | K18: 78.2 | L18: 48.8 | M18: 53.9 | N18: 59.2 | O18: 62.3 | P18: 68.9 | Q18: 65.9 | R18: 72.8
... B29: Total do Ativo | C29: Total assets | D29: 4024.2 | E29: 4194.4 | F29: 4436.4 | G29: 4659.3 | H29: 5131.9 | I29: 5435.1 | J29: 5634.6 | K29: 5975.9 | L29: 5723.5 | M29: 6002.8 | N29: 14906.3 | O29: 15253.5 | P29: 15343.1 | Q29: 15516.8 | R29: 15516.3
B31: Passivo | C31: Liabilities
B32: Passivo circulante | C32: Current liabilities | D32: 1269.3 | E32: 1433 | F32: 1501 | G32: 1635.4 | H32: 1589.6 | I32: 1703.2 | J32: 2173.3 | K32: 2292.3 | L32: 1872.1 | M32: 1986.1 | N32: 3706.2 | O32: 4517.1 | P32: 4562.1 | Q32: 4272.6 | R32: 3625.6
B33: Empréstimos e financiamentos | C33: Loans and financing | D33: 268.5 | E33: 345 | F33: 401.4 | G33: 392.3 | H33: 663 | I33: 642.5 | J33: 1087.4 | K33: 882.2 | L33: 747.5 | M33: 823 | N33: 903.2 | O33: 1476.5 | P33: 1904.1 | Q33: 1741.3 | R33: 1010.7
B34: Fornecedores | C34: Suppliers | D34: 588.7 | E34: 566 | F34: 637.5 | G34: 671.7 | H34: 571.5 | I34: 483.4 | J34: 569.1 | K34: 834.5 | L34: 647.5 | M34: 745 | N34: 1771.7 | O34: 1817.8 | P34: 1641.9 | Q34: 1524.3 | R34: 1552.1
B35: Instrumentos financeiros derivativos | C35: Financial Instruments - Derivatives | D35: 23.6 | E35: 13 | F35: 13.5 | G35: 1.8 | H35: 26.2 | I35: 72.2 | J35: 41.9 | K35: 59.5 | L35: 19.3 | M35: 0 | N35: 4.3 | O35: 0 | P35: 6.3 | Q35: 36.7 | R35: 9.1
B36: Arrendamento | C36: Lease | D36: 58.2 | E36: 62.1 | F36: 72.3 | G36: 89.6 | H36: 93.8 | I36: 97.5 | J36: 101.6 | K36: 107.7 | L36: 94.5 | M36: 96.8 | N36: 201.6 | O36: 213.1 | P36: 210.1 | Q36: 208.7 | R36: 226.2
B37: Imposto de renda e contribuição social a pagar | C37: Income tax and social contribution payable | D37: 38.1 | E37: 22 | F37: 12.7 | G37: 14.3 | H37: 8.5 | I37: 12.7 | J37: 29.1 | K37: 2.7 | L37: 10.3 | M37: 3.1 | N37: 0 | O37: 0 | P37: 0 | Q37: 0 | R37: 0
B38: Obrigações fiscais e sociais | C38: Fiscal and social obligations | D38: 49.3 | E38: 42.6 | F38: 31.2 | G38: 59.4 | H38: 38.2 | I38: 52.4 | J38: 59.2 | K38: 100.5 | L38: 84.1 | M38: 79.6 | N38: 205.9 | O38: 269.3 | P38: 207.3 | Q38: 231.2 | R38: 234.8
B39: Obrigações trabalhistas | C39: Employee-related obligations | D39: 68.3 | E39: 93.8 | F39: 123.8 | G39: 145.4 | H39: 75.9 | I39: 89.5 | J39: 100.8 | K39: 103.9 | L39: 85.8 | M39: 107 | N39: 361.6 | O39: 351.5 | P39: 364.6 | Q39: 331 | R39: 329.5
B40: Dividendos e juros sobre capital próprio | C40: Dividends and interest on equity | D40: 0 | E40: 111.6 | F40: 50 | G40: 72.2 | H40: 0 | I40: 82.8 | J40: 0 | K40: 0 | L40: 0 | M40: 0 | N40: 0 | O40: 0 | P40: 0 | Q40: 0 | R40: 0
B41: Parcelamento de impostos | C41: Tax installment | D41: 0 | E41: 0 | F41: 0 | G41: 0 | H41: 0 | I41: 0 | J41: 0 | K41: 1.9 | L41: 10.8 | M41: 9.3 | N41: 18.4 | O41: 17.6 | P41: 16.9 | Q41: 19.8 | R41: 14.2
B42: Obrigações a pagar na aquisição de controlada | C42: Payables from acquisition of subsidiary | D42: 100 | E42: 103.1 | F42: 83.2 | G42: 75.6 | H42: 32.6 | I42: 78.4 | J42: 78.8 | K42: 79.3 | L42: 48.1 | M42: 9.6 | N42: 30.6 | O42: 31.5 | P42: 0 | Q42: 0 | R42: 75
B43: Outras obrigações | C43: Other liabilities | D43: 74.6 | E43: 73.8 | F43: 75.4 | G43: 113.1 | H43: 79.9 | I43: 91.8 | J43: 105.4 | K43: 118.8 | L43: 122.9 | M43: 111.4 | N43: 207.6 | O43: 338.5 | P43: 209.6 | Q43: 178.3 | R43: 172.7
... B47: Arrendamento | C47: Lease | D47: 168.8 | E47: 180.1 | F47: 236.8 | G47: 284.9 | H47: 339.9 | I47: 395 | J47: 401.9 | K47: 407.5 | L47: 370.5 | M47: 368.7 | N47: 626.2 | O47: 662.5 | P47: 623.3 | Q47: 599.7 | R47: 564.9
B48: Partes relacionadas | C48: Related parties | D48: 0 | E48: - | F48: - | G48: - | H48: - | I48: - | J48: - | K48: - | L48: - | M48: - | N48: 0 | O48: 0 | P48: 0 | Q48: 0 | R48: 0
B49: Provisões para riscos trabalhistas, fiscais e cíveis | C49: Provisions for labor, tax, and civil risks | D49: 14.2 | E49: 14.4 | F49: 16.6 | G49: 17.8 | H49: 17.1 | I49: 19.2 | J49: 17.2 | K49: 16.1 | L49: 15.6 | M49: 17.5 | N49: 649.3 | O49: 675.5 | P49: 578.3 | Q49: 586.8 | R49: 584.8
B50: Outras obrigações | C50: Other liabilities | D50: 2.1 | E50: 2.2 | F50: 2.5 | G50: 2.5 | H50: 2.7 | I50: 2.8 | J50: 0 | K50: 0 | L50: 0 | M50: 0 | N50: 20.7 | O50: 25.6 | P50: 16 | Q50: 10 | R50: 9
B51: Impostos diferidos | C51: Deferred tax | D51: 2.9 | E51: 2.7 | F51: 3.5 | G51: 3.4 | H51: 1.7 | I51: 0.8 | J51: 1.3 | K51: 0 | L51: 0 | M51: 0 | N51: 239.9 | O51: 245.6 | P51: 226.4 | Q51: 222.7 | R51: 215
B52: Obrigações a pagar na aquisição de controlada | C52: Payables from acquisition of subsidiary | D52: 52 | E52: 58 | F52: 51 | G52: 51.1 | H52: 41.9 | I52: 42.2 | J52: 42.3 | K52: 42.4 | L52: 121.7 | M52: 120.5 | N52: 191.1 | O52: 196.1 | P52: 168.5 | Q52: 171.7 | R52: 94.1
B53: Parcelamento de impostos | C53: Tax installment | D53: 1 | E53: 1.2 | F53: - | G53: - | H53: - | I53: - | J53: 6.7 | K53: 6.3 | L53: 29.8 | M53: 28.7 | N53: 29.2 | O53: 27.6 | P53: 24.8 | Q53: 18.6 | R53: 20.5
B54: Instrumentos financeiros - derivativos | C54: Financial Instruments - Derivatives | D54: 0 | E54: 0 | F54: 0 | G54: 0 | H54: 0 | I54: 80.7 | J54: 77.5 | K54: 78.2 | L54: 0 | M54: 0 | N54: 0 | O54: 0 | P54: 0 | Q54: 0 | R54: 0
B55: Receitas diferidas | C55: Deferred revenue | D55: 0 | E55: - | F55: - | G55: - | H55: - | I55: - | J55: - | K55: 5.1 | L55: 5.1 | M55: 4.4 | N55: 4.1 | O55: 3.8 | P55: 3.5 | Q55: 3.1 | R55: 2.8
B56: Patrimônio líquido | C56: Shareholder's Equity | D56: 2498.3 | E56: 2492.5 | F56: 2614.9 | G56: 2654.6 | H56: 2741.9 | I56: 2805.7 | J56: 2909.3 | K56: 2929.1 | L56: 2957.5 | M56: 3087.4 | N56: 7883.8 | O56: 7721.5 | P56: 7804.4 | Q56: 8339.6 | R56: 8347.7
B57: Capital social | C57: Equity Capital | D57: 1645.5 | E57: 1645.5 | F57: 1671.7 | G57: 1671.7 | H57: 1671.7 | I57: 1738.2 | J57: 1738.2 | K57: 1738.2 | L57: 1738.2 | M57: 1738.2 | N57: 2317.2 | O57: 2317.2 | P57: 2317.2 | Q57: 2317.2 | R57: 2317.2
B58: Ações em tesouraria | C58: Treasury Shares | D58: -3.1 | E58: -3.1 | F58: 0 | G58: 0 | H58: -6.2 | I58: -9.3 | J58: -7.8 | K58: -9.9 | L58: -9.9 | M58: -1.8 | N58: -1.3 | O58: -1.2 | P58: -1.2 | Q58: -11.2 | R58: -168
B59: Reserva de capital | C59: Capital reserve | D59: 166.7 | E59: 166.2 | F59: 161.6 | G59: 176.1 | H59: 180.5 | I59: 177.7 | J59: 172.3 | K59: 183.9 | L59: 149.2 | M59: 153.2 | N59: 4228.6 | O59: 4234.7 | P59: 4240 | Q59: 4245.8 | R59: 4252.2
B60: Reservas de lucros | C60: Profit reserves | D60: 232.4 | E60: 232.4 | F60: 232.4 | G60: 253.6 | H60: 253.6 | I60: 159.4 | J60: 159.4 | K60: 120.5 | L60: 120.5 | M60: 120.5 | N60: 120.5 | O60: 283.5 | P60: 283.5 | Q60: 283.5 | R60: 283.5
B61: Reservas de incentivos fiscais | C61: Tax incentive reserves | D61: 309.1 | E61: 309.1 | F61: 309.1 | G61: 560.8 | H61: 560.8 | I61: 560.8 | J61: 560.8 | K61: 879.1 | L61: 879.1 | M61: 879.1 | N61: 879.1 | O61: 879.1 | P61: 879.1 | Q61: 879.1 | R61: 879.1
B62: Ajuste de avaliação patrimonial | C62: Adjustment of Equity Valuation | D62: -1.1 | E62: -6.4 | F62: -8.7 | G62: -8.4 | H62: -6.9 | I62: -7.5 | J62: -9.1 | K62: 2 | L62: -10 | M62: -21.9 | N62: -23.2 | O62: -6.3 | P62: -26.8 | Q62: -24.8 | R62: -30.9
B63: Outros resultados abrangentes | C63: Comprehensive income | D63: 0 | E63: - | F63: - | G63: - | H63: - | I63: - | J63: - | K63: -4.2 | L63: - | M63: - | N63: -4.4 | O63: -4.4 | P63: -5.2 | Q63: -5.5 | R63: -5.8
B64: Resultado do período | C64: Period Profit | D64: 98.1 | E64: 148.8 | F64: 248 | G64: 0 | H64: 63.1 | I64: 163.8 | J64: 277.6 | K64: 0 | L64: 73.1 | M64: 202.5 | N64: 349 | O64: 0 | P64: 117.8 | Q64: 655.5 | R64: 820.4
B65: Dividendos adicionais propostos | C65: Proposed additional dividends | D65: 50 | E65: - | F65: - | G65: - | H65: 0 | I65: - | J65: - | K65: - | L65: - | M65: - | N65: 0 | O65: 0 | P65: 0 | Q65: 0 | R65: 0
B66: Participação não controladores | C66: Non-controlling interest stake | D66: 0.7 | E66: 0 | F66: 0.8 | G66: 0.8 | H66: 25.3 | I66: 22.6 | J66: 17.9 | K66: 19.5 | L66: 17.3 | M66: 17.6 | N66: 18.3 | O66: 18.9 | P66: 0 | Q66: 0 | R66: 0
B67: Total do Passivo | C67: Total do Passivo | D67: 4024.2 | E67: 4194.4 | F67: 4436.4 | G67: 4659.3 | H67: 5131.9 | I67: 5435.1 | J67: 5634.6 | K67: 5975.9 | L67: 5723.5 | M67: 6002.8 | N67: 14906.3 | O67: 15253.5 | P67: 15343.1 | Q67: 15516.8 | R67: 15516.3
C70: Net Revenue | D70: ='P&L Adjusted Pro Forma'!D9 -> 1916.7 | E70: ='P&L Adjusted Pro Forma'!E9 -> 2210.8 | F70: ='P&L Adjusted Pro Forma'!F9 -> 2503.1 | G70: ='P&L Adjusted Pro Forma'!G9 -> 2749.3 | H70: ='P&L Adjusted Pro Forma'!H9 -> 2297.9 | I70: ='P&L Adjusted Pro Forma'!I9 -> 2496.7 | J70: ='P&L Adjusted Pro Forma'!J9 -> 2714.7 | K70: ='P&L Adjusted Pro Forma'!K9 -> 3001.3 | ... AQ70: ='P&L Adjusted Pro Forma'!AQ9 -> 3935.4684
C71: COGS | D71: =-'P&L Adjusted Pro Forma'!D10 -> 889.6 | E71: =-'P&L Adjusted Pro Forma'!E10 -> 951.9 | F71: =-'P&L Adjusted Pro Forma'!F10 -> 1132.9 | G71: =-'P&L Adjusted Pro Forma'!G10 -> 1282.8 | H71: =-'P&L Adjusted Pro Forma'!H10 -> 1057.9 | I71: =-'P&L Adjusted Pro Forma'!I10 -> 1105.6 | J71: =-'P&L Adjusted Pro Forma'!J10 -> 1226.7 | K71: =-'P&L Adjusted Pro Forma'!K10 -> 1318.1 | ... AQ71: =-'P&L Adjusted Pro Forma'!AQ10 -> 1771.239
C72: Days | D72: 365 | E72: 365 | F72: 365 | G72: 365 | H72: 365 | I72: 365 | J72: 365 | K72: 365 | L72: 366 | M72: 366 | N72: 366 | O72: 366 | P72: 365 | Q72: 365 | R72: 365 | S72: 365 | T72: 365 | U72: 365 | V72: 365 | W72: 365 | X72: 365 | Y72: 365 | Z72: 365 | AA72: 365 | AB72: 366 | AC72: 366 | AD72: 366 | AE72: 366 | AF72: 365 | AG72: 365 | AH72: 365 | AI72: 365 | AJ72: 365 | AK72: 365 | AL72: 365 | AM72: 365 | AN72: 365 | AO72: 365 | AP72: 365 | AQ72: 365
C74: Financial Investments | D74: =D9 -> 603.6 | E74: =E9 -> 633.6 | F74: =F9 -> 471.2 | G74: =G9 -> 447.6 | H74: =H9 -> 699.5 | I74: =I9 -> 608.6 | J74: =J9 -> 582.9 | K74: =K9 -> 676.4 | ... R74: =R9 -> 560.6 | S74: =S75*S70/S72 -> 598.96868 | T74: =T75*T70/T72 -> 310.01062 | U74: =U75*U70/U72 -> 326.00377 | V74: =V75*V70/V72 -> 342.94053 | W74: =W75*W70/W72 -> 360.85684 | X74: =X75*X70/X72 -> 379.78368 | Y74: =Y75*Y70/Y72 -> 399.74479 | Z74: =Z75*Z70/Z72 -> 420.75393 | ... AQ74: =AQ75*AQ70/AQ72 -> 742.88626
C75: Days of Revenue | D75: =D74*D72/D70 -> 114.94444 | E75: =E74*E72/E70 -> 104.60648 | F75: =F74*F72/F70 -> 68.71 | G75: =G74*G72/G70 -> 59.423853 | H75: =H74*H72/H70 -> 111.10906 | I75: =I74*I72/I70 -> 88.973044 | J75: =J74*J72/J70 -> 78.372748 | K75: =K74*K72/K70 -> 82.259687 | ... R75: =R74*R72/R70 -> 68.899926 | S75: =R75 -> 68.899926 | T75: =S75 -> 68.899926 | U75: =T75 -> 68.899926 | V75: =U75 -> 68.899926 | W75: =V75 -> 68.899926 | X75: =W75 -> 68.899926 | Y75: =X75 -> 68.899926 | Z75: =Y75 -> 68.899926 | ... AQ75: =AP75 -> 68.899926
C77: Trade accounts receivables | D77: =D10 -> 631.3 | E77: =E10 -> 613.7 | F77: =F10 -> 722 | G77: =G10 -> 867.6 | H77: =H10 -> 743 | I77: =I10 -> 781.5 | J77: =J10 -> 921.8 | K77: =K10 -> 1125.4 | ... R77: =R10 -> 2577 | S77: =S78*S70/S72 -> 2753.3755 | T77: =T78*T70/T72 -> 1425.0756 | U77: =U78*U70/U72 -> 1498.5939 | V77: =V78*V70/V72 -> 1576.4498 | W77: =W78*W70/W72 -> 1658.8086 | X77: =X78*X70/X72 -> 1745.8126 | Y77: =Y78*Y70/Y72 -> 1837.571 | Z77: =Z78*Z70/Z72 -> 1934.1471 | ... AQ77: =AQ78*AQ70/AQ72 -> 3414.9445
C78: Days of Revenue | D78: =D77*D72/D70 -> 120.21939 | E78: =E77*E72/E70 -> 101.32102 | F78: =F77*F72/F70 -> 105.28145 | G78: =G77*G72/G70 -> 115.1835 | H78: =H77*H72/H70 -> 118.01863 | I78: =I77*I72/I70 -> 114.24981 | J78: =J77*J72/J70 -> 123.93893 | K78: =K77*K72/K70 -> 136.86436 | ... R78: =R77*R72/R70 -> 316.72335 | S78: =R78 -> 316.72335 | T78: =S78 -> 316.72335 | U78: =T78 -> 316.72335 | V78: =U78 -> 316.72335 | W78: =V78 -> 316.72335 | X78: =W78 -> 316.72335 | Y78: =X78 -> 316.72335 | Z78: =Y78 -> 316.72335 | ... AQ78: =AP78 -> 316.72335
C80: Inventory | D80: =D11 -> 556.7 | E80: =E11 -> 651.7 | F80: =F11 -> 755.1 | G80: =G11 -> 772.1 | H80: =H11 -> 842.5 | I80: =I11 -> 864.5 | J80: =J11 -> 866.8 | K80: =K11 -> 774.3 | ... R80: =R11 -> 2480.7 | S80: =S81*S71/S72 -> 2632.2093 | T80: =T81*T71/T72 -> 1362.3631 | U80: =U81*U71/U72 -> 1432.6461 | V80: =V81*V71/V72 -> 1507.0758 | W80: =W81*W71/W72 -> 1585.8103 | X80: =X81*X71/X72 -> 1668.9856 | Y80: =Y81*Y71/Y72 -> 1756.7061 | Z80: =Z81*Z71/Z72 -> 1849.0322 | ... AQ80: =AQ81*AQ71/AQ72 -> 3264.665
C81: Days of COGS | D81: =D80*D72/D71 -> 228.41221 | E81: =E80*E72/E71 -> 249.89022 | F81: =F80*F72/F71 -> 243.27964 | G81: =G80*G72/G71 -> 219.68857 | H81: =H80*H72/H71 -> 290.68201 | I81: =I80*I72/I71 -> 285.40385 | J81: =J80*J72/J71 -> 257.9131 | K81: =K80*K72/K71 -> 214.41431 | ... R81: =R80*R72/R71 -> 672.75095 | S81: =R81 -> 672.75095 | T81: =S81 -> 672.75095 | U81: =T81 -> 672.75095 | V81: =U81 -> 672.75095 | W81: =V81 -> 672.75095 | X81: =W81 -> 672.75095 | Y81: =X81 -> 672.75095 | Z81: =Y81 -> 672.75095 | ... AQ81: =AP81 -> 672.75095
C83: Financial Instruments - Derivatives | D83: =D12 -> 0.5 | E83: =E12 -> 0 | F83: =F12 -> 0 | G83: =G12 -> 0 | H83: =H12 -> 0 | I83: =I12 -> 0 | J83: =J12 -> 0 | K83: =K12 -> 0 | ... R83: =R12 -> 18.7 | S83: =S84*S70/S72 -> 19.979869 | T83: =T84*T70/T72 -> 10.341061 | U83: =U84*U70/U72 -> 10.874546 | V83: =V84*V70/V72 -> 11.439507 | W83: =W84*W70/W72 -> 12.037144 | X83: =X84*X70/X72 -> 12.668489 | Y83: =Y84*Y70/Y72 -> 13.334334 | Z83: =Z84*Z70/Z72 -> 14.035138 | ... AQ83: =AQ84*AQ70/AQ72 -> 24.780544
C84: Days of Revenue | D84: =D83*D72/D70 -> 0.095215735 | E84: =E83*E72/E70 -> 0 | F84: =F83*F72/F70 -> 0 | G84: =G83*G72/G70 -> 0 | H84: =H83*H72/H70 -> 0 | I84: =I83*I72/I70 -> 0 | J84: =J83*J72/J70 -> 0 | K84: =K83*K72/K70 -> 0 | ... R84: =R83*R72/R70 -> 2.2983029 | S84: =R84 -> 2.2983029 | T84: =S84 -> 2.2983029 | U84: =T84 -> 2.2983029 | V84: =U84 -> 2.2983029 | W84: =V84 -> 2.2983029 | X84: =W84 -> 2.2983029 | Y84: =X84 -> 2.2983029 | Z84: =Y84 -> 2.2983029 | ... AQ84: =AP84 -> 2.2983029
C86: Taxes recoverable | D86: =D13 -> 127.4 | E86: =E13 -> 148.2 | F86: =F13 -> 169 | G86: =G13 -> 187.5 | H86: =H13 -> 203.2 | I86: =I13 -> 231.7 | J86: =J13 -> 145 | K86: =K13 -> 111.7 | ... R86: =R13 -> 381.6 | S86: =S87*S71/S72 -> 404.9063 | T86: =T87*T71/T72 -> 209.56897 | U86: =U87*U71/U72 -> 220.38044 | V86: =V87*V71/V72 -> 231.82978 | W86: =W87*W71/W72 -> 243.94132 | X86: =X87*X71/X72 -> 256.73597 | Y86: =Y87*Y71/Y72 -> 270.22979 | Z86: =Z87*Z71/Z72 -> 284.4321 | ... AQ86: =AQ87*AQ71/AQ72 -> 502.19541
C87: Days of COGS | D87: =D86*D72/D71 -> 52.271808 | E87: =E86*E72/E71 -> 56.826347 | F87: =F86*F72/F71 -> 54.44876 | G87: =G86*G72/G71 -> 53.350094 | H87: =H86*H72/H71 -> 70.108706 | I87: =I86*I72/I71 -> 76.492855 | J87: =J86*J72/J71 -> 43.144208 | K87: =K86*K72/K71 -> 30.931265 | ... R87: =R86*R72/R71 -> 103.48763 | S87: =R87 -> 103.48763 | T87: =S87 -> 103.48763 | U87: =T87 -> 103.48763 | V87: =U87 -> 103.48763 | W87: =V87 -> 103.48763 | X87: =W87 -> 103.48763 | Y87: =X87 -> 103.48763 | Z87: =Y87 -> 103.48763 | ... AQ87: =AP87 -> 103.48763
C89: Recovarable Income Tax and Social Contribution | D89: =D14 -> 2.6 | E89: =E14 -> 13.6 | F89: =F14 -> 14.4 | G89: =G14 -> 13.7 | H89: =H14 -> 19.3 | I89: =I14 -> 25.3 | J89: =J14 -> 5 | K89: =K14 -> 17.9 | ... R89: =R14 -> 298.7 | S89: =S90*S71/S72 -> 316.94316 | T89: =T90*T71/T72 -> 164.04154 | U89: =U90*U71/U72 -> 172.50429 | V89: =V90*V71/V72 -> 181.46634 | W89: =W90*W71/W72 -> 190.94673 | X89: =X90*X71/X72 -> 200.96183 | Y89: =Y90*Y71/Y72 -> 211.52421 | Z89: =Z90*Z71/Z72 -> 222.64116 | ... AQ89: =AQ90*AQ71/AQ72 -> 393.09688
C90: Days of COGS | D90: =D89*D72/D71 -> 1.0667716 | E90: =E89*E72/E71 -> 5.2148335 | F90: =F89*F72/F71 -> 4.639421 | G90: =G89*G72/G71 -> 3.8981135 | H90: =H89*H72/H71 -> 6.658947 | I90: =I89*I72/I71 -> 8.3524783 | J90: =J89*J72/J71 -> 1.4877313 | K90: =K89*K72/K71 -> 4.9567559 | ... R90: =R89*R72/R71 -> 81.005647 | S90: =R90 -> 81.005647 | T90: =S90 -> 81.005647 | U90: =T90 -> 81.005647 | V90: =U90 -> 81.005647 | W90: =V90 -> 81.005647 | X90: =W90 -> 81.005647 | Y90: =X90 -> 81.005647 | Z90: =Y90 -> 81.005647 | ... AQ90: =AP90 -> 81.005647
C92: Other credits | D92: =D15 -> 80.6 | E92: =E15 -> 50.4 | F92: =F15 -> 85.2 | G92: =G15 -> 66.1 | H92: =H15 -> 99.9 | I92: =I15 -> 105.4 | J92: =J15 -> 101.7 | K92: =K15 -> 136.1 | ... R92: =R15 -> 382.3 | S92: =S93*S70/S72 -> 408.46544 | T92: =T93*T70/T72 -> 211.41109 | U92: =U93*U70/U72 -> 222.31759 | V92: =V93*V70/V72 -> 233.86758 | W92: =W93*W70/W72 -> 246.08557 | X92: =X93*X70/X72 -> 258.99269 | Y92: =Y93*Y70/Y72 -> 272.60512 | Z92: =Z93*Z70/Z72 -> 286.93227 | ... AQ92: =AQ93*AQ70/AQ72 -> 506.60973
C93: Days of Revenue | D93: =D92*D72/D70 -> 15.348777 | E93: =E92*E72/E70 -> 8.3209698 | F93: =F92*F72/F70 -> 12.423794 | G93: =G92*G72/G70 -> 8.7755065 | H93: =H92*H72/H70 -> 15.868184 | I93: =I92*I72/I70 -> 15.40874 | J93: =J92*J72/J70 -> 13.673887 | K93: =K92*K72/K70 -> 16.551661 | ... R93: =R92*R72/R70 -> 46.986161 | S93: =R93 -> 46.986161 | T93: =S93 -> 46.986161 | U93: =T93 -> 46.986161 | V93: =U93 -> 46.986161 | W93: =V93 -> 46.986161 | X93: =W93 -> 46.986161 | Y93: =X93 -> 46.986161 | Z93: =Y93 -> 46.986161 | ... AQ93: =AP93 -> 46.986161
C95: Operational Assets | D95: =D92+D89+D86+D83+D80+D77+D74 -> 2002.7 | E95: =E92+E89+E86+E83+E80+E77+E74 -> 2111.2 | F95: =F92+F89+F86+F83+F80+F77+F74 -> 2216.9 | G95: =G92+G89+G86+G83+G80+G77+G74 -> 2354.6 | H95: =H92+H89+H86+H83+H80+H77+H74 -> 2607.4 | I95: =I92+I89+I86+I83+I80+I77+I74 -> 2617 | J95: =J92+J89+J86+J83+J80+J77+J74 -> 2623.2 | K95: =K92+K89+K86+K83+K80+K77+K74 -> 2841.8 | ... AQ95: =AQ92+AQ89+AQ86+AQ83+AQ80+AQ77+AQ74 -> 8849.1783
C97: Loans and financing | D97: =D33 -> 268.5 | E97: =E33 -> 345 | F97: =F33 -> 401.4 | G97: =G33 -> 392.3 | H97: =H33 -> 663 | I97: =I33 -> 642.5 | J97: =J33 -> 1087.4 | K97: =K33 -> 882.2 | ... R97: =R33 -> 1010.7 | S97: =S98*S71/S72 -> 1072.4287 | T97: =T98*T71/T72 -> 555.06122 | U97: =U98*U71/U72 -> 583.6963 | V97: =V98*V71/V72 -> 614.02086 | W97: =W98*W71/W72 -> 646.09929 | X97: =X98*X71/X72 -> 679.98701 | Y97: =Y98*Y71/Y72 -> 715.72654 | Z97: =Z98*Z71/Z72 -> 753.34255 | ... AQ97: =AQ98*AQ71/AQ72 -> 1330.1072
C98: Days of COGS | D98: =D97*D72/D71 -> 110.16468 | E98: =E97*E72/E71 -> 132.28806 | F98: =F97*F72/F71 -> 129.32386 | G98: =G97*G72/G71 -> 111.62262 | H98: =H97*H72/H71 -> 228.75035 | I98: =I97*I72/I71 -> 212.11333 | J98: =J97*J72/J71 -> 323.55181 | K98: =K97*K72/K71 -> 244.2933 | ... R98: =R97*R72/R71 -> 274.09577 | S98: =R98 -> 274.09577 | T98: =S98 -> 274.09577 | U98: =T98 -> 274.09577 | V98: =U98 -> 274.09577 | W98: =V98 -> 274.09577 | X98: =W98 -> 274.09577 | Y98: =X98 -> 274.09577 | Z98: =Y98 -> 274.09577 | ... AQ98: =AP98 -> 274.09577
C100: Suppliers | D100: =34 -> 34 | E100: =34 -> 34 | F100: =34 -> 34 | G100: =34 -> 34 | H100: =34 -> 34 | I100: =34 -> 34 | J100: =34 -> 34 | K100: =34 -> 34 | ... R100: =34 -> 34 | S100: =S101*S71/S72 -> 36.076557 | T100: =T101*T71/T72 -> 18.672288 | U100: =U101*U71/U72 -> 19.635574 | V100: =V101*V71/V72 -> 20.655693 | W100: =W101*W71/W72 -> 21.734813 | X100: =X101*X71/X72 -> 22.874798 | Y100: =Y101*Y71/Y72 -> 24.077078 | Z100: =Z101*Z71/Z72 -> 25.342482 | ... AQ100: =AQ101*AQ71/AQ72 -> 44.744874
C101: Days of COGS | D101: =D100*D72/D71 -> 13.95009 | E101: =E100*E72/E71 -> 13.037084 | F101: =F100*F72/F71 -> 10.954188 | G101: =G100*G72/G71 -> 9.6741503 | H101: =H100*H72/H71 -> 11.730787 | I101: =I100*I72/I71 -> 11.224674 | J101: =J100*J72/J71 -> 10.116573 | K101: =K100*K72/K71 -> 9.4150671 | ... R101: =R100*R72/R71 -> 9.2205959 | S101: =R101 -> 9.2205959 | T101: =S101 -> 9.2205959 | U101: =T101 -> 9.2205959 | V101: =U101 -> 9.2205959 | W101: =V101 -> 9.2205959 | X101: =W101 -> 9.2205959 | Y101: =X101 -> 9.2205959 | Z101: =Y101 -> 9.2205959 | ... AQ101: =AP101 -> 9.2205959
C103: Financial Instruments - Derivatives | D103: =35 -> 35 | E103: =35 -> 35 | F103: =35 -> 35 | G103: =35 -> 35 | H103: =35 -> 35 | I103: =35 -> 35 | J103: =35 -> 35 | K103: =35 -> 35 | ... R103: =35 -> 35 | S103: =S104*S71/S72 -> 37.137632 | T103: =T104*T71/T72 -> 19.221473 | U103: =U104*U71/U72 -> 20.21309 | V103: =V104*V71/V72 -> 21.263214 | W103: =W104*W71/W72 -> 22.374073 | X103: =X104*X71/X72 -> 23.547586 | Y103: =Y104*Y71/Y72 -> 24.785227 | Z103: =Z104*Z71/Z72 -> 26.087849 | ... AQ103: =AQ104*AQ71/AQ72 -> 46.0609
C104: Days of COGS | D104: =D103*D72/D71 -> 14.360387 | E104: =E103*E72/E71 -> 13.420527 | F104: =F103*F72/F71 -> 11.27637 | G104: =G103*G72/G71 -> 9.9586841 | H104: =H103*H72/H71 -> 12.075811 | I104: =I103*I72/I71 -> 11.554812 | J104: =J103*J72/J71 -> 10.414119 | K104: =K103*K72/K71 -> 9.6919809 | ... R104: =R103*R72/R71 -> 9.4917899 | S104: =R104 -> 9.4917899 | T104: =S104 -> 9.4917899 | U104: =T104 -> 9.4917899 | V104: =U104 -> 9.4917899 | W104: =V104 -> 9.4917899 | X104: =W104 -> 9.4917899 | Y104: =X104 -> 9.4917899 | Z104: =Y104 -> 9.4917899 | ... AQ104: =AP104 -> 9.4917899
C106: Lease | D106: =36 -> 36 | E106: =36 -> 36 | F106: =36 -> 36 | G106: =36 -> 36 | H106: =36 -> 36 | I106: =36 -> 36 | J106: =36 -> 36 | K106: =36 -> 36 | ... R106: =36 -> 36 | S106: =S107*S71/S72 -> 38.198707 | T106: =T107*T71/T72 -> 19.770658 | U106: =U107*U71/U72 -> 20.790607 | V106: =V107*V71/V72 -> 21.870734 | W106: =W107*W71/W72 -> 23.013332 | X106: =X107*X71/X72 -> 24.220374 | Y106: =Y107*Y71/Y72 -> 25.493376 | Z106: =Z107*Z71/Z72 -> 26.833217 | ... AQ106: =AQ107*AQ71/AQ72 -> 47.376926
C107: Days of COGS | D107: =D106*D72/D71 -> 14.770683 | E107: =E106*E72/E71 -> 13.803971 | F107: =F106*F72/F71 -> 11.598552 | G107: =G106*G72/G71 -> 10.243218 | H107: =H106*H72/H71 -> 12.420834 | I107: =I106*I72/I71 -> 11.884949 | J107: =J106*J72/J71 -> 10.711665 | K107: =K106*K72/K71 -> 9.9688946 | ... R107: =R106*R72/R71 -> 9.7629839 | S107: =R107 -> 9.7629839 | T107: =S107 -> 9.7629839 | U107: =T107 -> 9.7629839 | V107: =U107 -> 9.7629839 | W107: =V107 -> 9.7629839 | X107: =W107 -> 9.7629839 | Y107: =X107 -> 9.7629839 | Z107: =Y107 -> 9.7629839 | ... AQ107: =AP107 -> 9.7629839
C109: Income tax and social contribution payable | D109: =37 -> 37 | E109: =37 -> 37 | F109: =37 -> 37 | G109: =37 -> 37 | H109: =37 -> 37 | I109: =37 -> 37 | J109: =37 -> 37 | K109: =37 -> 37 | ... R109: =37 -> 37 | S109: =S110*S71/S72 -> 39.259783 | T109: =T110*T71/T72 -> 20.319843 | U109: =U110*U71/U72 -> 21.368124 | V109: =V110*V71/V72 -> 22.478255 | W109: =W110*W71/W72 -> 23.652591 | X109: =X110*X71/X72 -> 24.893162 | Y109: =Y110*Y71/Y72 -> 26.201526 | Z109: =Z110*Z71/Z72 -> 27.578584 | ... AQ109: =AQ110*AQ71/AQ72 -> 48.692951
C110: Days of COGS | D110: =D109*D72/D71 -> 15.18098 | E110: =E109*E72/E71 -> 14.187415 | F110: =F109*F72/F71 -> 11.920734 | G110: =G109*G72/G71 -> 10.527752 | H110: =H109*H72/H71 -> 12.765857 | I110: =I109*I72/I71 -> 12.215087 | J110: =J109*J72/J71 -> 11.009212 | K110: =K109*K72/K71 -> 10.245808 | ... R110: =R109*R72/R71 -> 10.034178 | S110: =R110 -> 10.034178 | T110: =S110 -> 10.034178 | U110: =T110 -> 10.034178 | V110: =U110 -> 10.034178 | W110: =V110 -> 10.034178 | X110: =W110 -> 10.034178 | Y110: =X110 -> 10.034178 | Z110: =Y110 -> 10.034178 | ... AQ110: =AP110 -> 10.034178
C112: Fiscal and social obligations | D112: =38 -> 38 | E112: =38 -> 38 | F112: =38 -> 38 | G112: =38 -> 38 | H112: =38 -> 38 | I112: =38 -> 38 | J112: =38 -> 38 | K112: =38 -> 38 | ... R112: =38 -> 38 | S112: =S113*S71/S72 -> 40.320858 | T112: =T113*T71/T72 -> 20.869028 | U112: =U113*U71/U72 -> 21.945641 | V112: =V113*V71/V72 -> 23.085775 | W112: =W113*W71/W72 -> 24.29185 | X112: =X113*X71/X72 -> 25.565951 | Y112: =Y113*Y71/Y72 -> 26.909675 | Z112: =Z113*Z71/Z72 -> 28.323951 | ... AQ112: =AQ113*AQ71/AQ72 -> 50.008977
C113: Days of COGS | D113: =D112*D72/D71 -> 15.591277 | E113: =E112*E72/E71 -> 14.570858 | F113: =F112*F72/F71 -> 12.242916 | G113: =G112*G72/G71 -> 10.812286 | H113: =H112*H72/H71 -> 13.11088 | I113: =I112*I72/I71 -> 12.545224 | J113: =J112*J72/J71 -> 11.306758 | K113: =K112*K72/K71 -> 10.522722 | ... R113: =R112*R72/R71 -> 10.305372 | S113: =R113 -> 10.305372 | T113: =S113 -> 10.305372 | U113: =T113 -> 10.305372 | V113: =U113 -> 10.305372 | W113: =V113 -> 10.305372 | X113: =W113 -> 10.305372 | Y113: =X113 -> 10.305372 | Z113: =Y113 -> 10.305372 | ... AQ113: =AP113 -> 10.305372
C115: Employee-related obligations | D115: =39 -> 39 | E115: =39 -> 39 | F115: =39 -> 39 | G115: =39 -> 39 | H115: =39 -> 39 | I115: =39 -> 39 | J115: =39 -> 39 | K115: =39 -> 39 | ... R115: =39 -> 39 | S115: =S116*S71/S72 -> 41.381933 | T115: =T116*T71/T72 -> 21.418213 | U115: =U116*U71/U72 -> 22.523158 | V115: =V116*V71/V72 -> 23.693295 | W115: =W116*W71/W72 -> 24.931109 | X115: =X116*X71/X72 -> 26.238739 | Y115: =Y116*Y71/Y72 -> 27.617824 | Z115: =Z116*Z71/Z72 -> 29.069318 | ... AQ115: =AQ116*AQ71/AQ72 -> 51.325003
C116: Days of COGS | D116: =D115*D72/D71 -> 16.001574 | E116: =E115*E72/E71 -> 14.954302 | F116: =F115*F72/F71 -> 12.565098 | G116: =G115*G72/G71 -> 11.096819 | H116: =H115*H72/H71 -> 13.455903 | I116: =I115*I72/I71 -> 12.875362 | J116: =J115*J72/J71 -> 11.604304 | K116: =K115*K72/K71 -> 10.799636 | ... R116: =R115*R72/R71 -> 10.576566 | S116: =R116 -> 10.576566 | T116: =S116 -> 10.576566 | U116: =T116 -> 10.576566 | V116: =U116 -> 10.576566 | W116: =V116 -> 10.576566 | X116: =W116 -> 10.576566 | Y116: =X116 -> 10.576566 | Z116: =Y116 -> 10.576566 | ... AQ116: =AP116 -> 10.576566
C118: Dividends and interest on equity | D118: =40 -> 40 | E118: =40 -> 40 | F118: =40 -> 40 | G118: =40 -> 40 | H118: =40 -> 40 | I118: =40 -> 40 | J118: =40 -> 40 | K118: =40 -> 40 | ... R118: =40 -> 40 | S118: =S119*S71/S72 -> 42.443008 | T118: =T119*T71/T72 -> 21.967398 | U118: =U119*U71/U72 -> 23.100675 | V118: =V119*V71/V72 -> 24.300816 | W118: =W119*W71/W72 -> 25.570369 | X118: =X119*X71/X72 -> 26.911527 | Y118: =Y119*Y71/Y72 -> 28.325974 | Z118: =Z119*Z71/Z72 -> 29.814685 | ... AQ118: =AQ119*AQ71/AQ72 -> 52.641028
C119: Days of COGS | D119: =D118*D72/D71 -> 16.411871 | E119: =E118*E72/E71 -> 15.337746 | F119: =F118*F72/F71 -> 12.88728 | G119: =G118*G72/G71 -> 11.381353 | H119: =H118*H72/H71 -> 13.800926 | I119: =I118*I72/I71 -> 13.205499 | J119: =J118*J72/J71 -> 11.90185 | K119: =K118*K72/K71 -> 11.07655 | ... R119: =R118*R72/R71 -> 10.84776 | S119: =R119 -> 10.84776 | T119: =S119 -> 10.84776 | U119: =T119 -> 10.84776 | V119: =U119 -> 10.84776 | W119: =V119 -> 10.84776 | X119: =W119 -> 10.84776 | Y119: =X119 -> 10.84776 | Z119: =Y119 -> 10.84776 | ... AQ119: =AP119 -> 10.84776
C121: Tax installment | D121: =41 -> 41 | E121: =41 -> 41 | F121: =41 -> 41 | G121: =41 -> 41 | H121: =41 -> 41 | I121: =41 -> 41 | J121: =41 -> 41 | K121: =41 -> 41 | ... R121: =41 -> 41 | S121: =S122*S71/S72 -> 43.504084 | T121: =T122*T71/T72 -> 22.516582 | U121: =U122*U71/U72 -> 23.678192 | V121: =V122*V71/V72 -> 24.908336 | W121: =W122*W71/W72 -> 26.209628 | X121: =X122*X71/X72 -> 27.584315 | Y121: =Y122*Y71/Y72 -> 29.034123 | Z121: =Z122*Z71/Z72 -> 30.560052 | ... AQ121: =AQ122*AQ71/AQ72 -> 53.957054
C122: Days of COGS | D122: =D121*D72/D71 -> 16.822167 | E122: =E121*E72/E71 -> 15.721189 | F122: =F121*F72/F71 -> 13.209462 | G122: =G121*G72/G71 -> 11.665887 | H122: =H121*H72/H71 -> 14.14595 | I122: =I121*I72/I71 -> 13.535637 | J122: =J121*J72/J71 -> 12.199397 | K122: =K121*K72/K71 -> 11.353463 | ... R122: =R121*R72/R71 -> 11.118954 | S122: =R122 -> 11.118954 | T122: =S122 -> 11.118954 | U122: =T122 -> 11.118954 | V122: =U122 -> 11.118954 | W122: =V122 -> 11.118954 | X122: =W122 -> 11.118954 | Y122: =X122 -> 11.118954 | Z122: =Y122 -> 11.118954 | ... AQ122: =AP122 -> 11.118954
C124: Payables from acquisition of subsidiary | D124: =42 -> 42 | E124: =42 -> 42 | F124: =42 -> 42 | G124: =42 -> 42 | H124: =42 -> 42 | I124: =42 -> 42 | J124: =42 -> 42 | K124: =42 -> 42 | ... R124: =42 -> 42 | S124: =S125*S71/S72 -> 44.565159 | T124: =T125*T71/T72 -> 23.065767 | U124: =U125*U71/U72 -> 24.255709 | V124: =V125*V71/V72 -> 25.515856 | W124: =W125*W71/W72 -> 26.848887 | X124: =X125*X71/X72 -> 28.257103 | Y124: =Y125*Y71/Y72 -> 29.742272 | Z124: =Z125*Z71/Z72 -> 31.305419 | ... AQ124: =AQ125*AQ71/AQ72 -> 55.27308
C125: Days of COGS | D125: =D124*D72/D71 -> 17.232464 | E125: =E124*E72/E71 -> 16.104633 | F125: =F124*F72/F71 -> 13.531644 | G125: =G124*G72/G71 -> 11.950421 | H125: =H124*H72/H71 -> 14.490973 | I125: =I124*I72/I71 -> 13.865774 | J125: =J124*J72/J71 -> 12.496943 | K125: =K124*K72/K71 -> 11.630377 | ... R125: =R124*R72/R71 -> 11.390148 | S125: =R125 -> 11.390148 | T125: =S125 -> 11.390148 | U125: =T125 -> 11.390148 | V125: =U125 -> 11.390148 | W125: =V125 -> 11.390148 | X125: =W125 -> 11.390148 | Y125: =X125 -> 11.390148 | Z125: =Y125 -> 11.390148 | ... AQ125: =AP125 -> 11.390148
C127: Other liabilities | D127: =43 -> 43 | E127: =43 -> 43 | F127: =43 -> 43 | G127: =43 -> 43 | H127: =43 -> 43 | I127: =43 -> 43 | J127: =43 -> 43 | K127: =43 -> 43 | ... R127: =43 -> 43 | S127: =S128*S71/S72 -> 45.626234 | T127: =T128*T71/T72 -> 23.614952 | U127: =U128*U71/U72 -> 24.833225 | V127: =V128*V71/V72 -> 26.123377 | W127: =W128*W71/W72 -> 27.488146 | X127: =X128*X71/X72 -> 28.929891 | Y127: =Y128*Y71/Y72 -> 30.450422 | Z127: =Z128*Z71/Z72 -> 32.050786 | ... AQ127: =AQ128*AQ71/AQ72 -> 56.589106
C128: Days of COGS | D128: =D127*D72/D71 -> 17.642761 | E128: =E127*E72/E71 -> 16.488076 | F128: =F127*F72/F71 -> 13.853826 | G128: =G127*G72/G71 -> 12.234955 | H128: =H127*H72/H71 -> 14.835996 | I128: =I127*I72/I71 -> 14.195912 | J128: =J127*J72/J71 -> 12.794489 | K128: =K127*K72/K71 -> 11.907291 | ... R128: =R127*R72/R71 -> 11.661342 | S128: =R128 -> 11.661342 | T128: =S128 -> 11.661342 | U128: =T128 -> 11.661342 | V128: =U128 -> 11.661342 | W128: =V128 -> 11.661342 | X128: =W128 -> 11.661342 | Y128: =X128 -> 11.661342 | Z128: =Y128 -> 11.661342 | ... AQ128: =AP128 -> 11.661342
C130: Deferred revenue | D130: =44 -> 44 | E130: =44 -> 44 | F130: =44 -> 44 | G130: =44 -> 44 | H130: =44 -> 44 | I130: =44 -> 44 | J130: =44 -> 44 | K130: =44 -> 44 | ... R130: =44 -> 44 | S130: =S131*S71/S72 -> 46.687309 | T130: =T131*T71/T72 -> 24.164137 | U130: =U131*U71/U72 -> 25.410742 | V130: =V131*V71/V72 -> 26.730897 | W130: =W131*W71/W72 -> 28.127405 | X130: =X131*X71/X72 -> 29.60268 | Y130: =Y131*Y71/Y72 -> 31.158571 | Z130: =Z131*Z71/Z72 -> 32.796154 | ... AQ130: =AQ131*AQ71/AQ72 -> 57.905131
C131: Days of COGS | D131: =D130*D72/D71 -> 18.053058 | E131: =E130*E72/E71 -> 16.87152 | F131: =F130*F72/F71 -> 14.176008 | G131: =G130*G72/G71 -> 12.519489 | H131: =H130*H72/H71 -> 15.181019 | I131: =I130*I72/I71 -> 14.526049 | J131: =J130*J72/J71 -> 13.092036 | K131: =K130*K72/K71 -> 12.184205 | ... R131: =R130*R72/R71 -> 11.932536 | S131: =R131 -> 11.932536 | T131: =S131 -> 11.932536 | U131: =T131 -> 11.932536 | V131: =U131 -> 11.932536 | W131: =V131 -> 11.932536 | X131: =W131 -> 11.932536 | Y131: =X131 -> 11.932536 | Z131: =Y131 -> 11.932536 | ... AQ131: =AP131 -> 11.932536
C133: Operacional Liabilities | D133: =D130+D127+D124+D121+D118+D115+D112+D109+D106+D103+D100+D97 -> 697.5 | E133: =E130+E127+E124+E121+E118+E115+E112+E109+E106+E103+E100+E97 -> 774 | F133: =F130+F127+F124+F121+F118+F115+F112+F109+F106+F103+F100+F97 -> 830.4 | G133: =G130+G127+G124+G121+G118+G115+G112+G109+G106+G103+G100+G97 -> 821.3 | H133: =H130+H127+H124+H121+H118+H115+H112+H109+H106+H103+H100+H97 -> 1092 | I133: =I130+I127+I124+I121+I118+I115+I112+I109+I106+I103+I100+I97 -> 1071.5 | J133: =J130+J127+J124+J121+J118+J115+J112+J109+J106+J103+J100+J97 -> 1516.4 | K133: =K130+K127+K124+K121+K118+K115+K112+K109+K106+K103+K100+K97 -> 1311.2 | ... AQ133: =AQ130+AQ127+AQ124+AQ121+AQ118+AQ115+AQ112+AQ109+AQ106+AQ103+AQ100+AQ97 -> 1894.6822
C135: Cash Convertion Cycle | D135: =D81+D78-D101 -> 334.68151 | E135: =E81+E78-E101 -> 338.17415 | F135: =F81+F78-F101 -> 337.6069 | G135: =G81+G78-G101 -> 325.19792 | H135: =H81+H78-H101 -> 396.96985 | I135: =I81+I78-I101 -> 388.42899 | J135: =J81+J78-J101 -> 371.73545 | K135: =K81+K78-K101 -> 341.8636 | ... AQ135: =AQ81+AQ78-AQ101 -> 980.2537
C137: Working Capital | D137: =D95-D133 -> 1305.2 | E137: =E95-E133 -> 1337.2 | F137: =F95-F133 -> 1386.5 | G137: =G95-G133 -> 1533.3 | H137: =H95-H133 -> 1515.4 | I137: =I95-I133 -> 1545.5 | J137: =J95-J133 -> 1106.8 | K137: =K95-K133 -> 1530.6 | ... AQ137: =AQ95-AQ133 -> 6954.4961
C139: Change in Working Capital | D139: =IFERROR(D137-C137, "N/A") -> N/A | E139: =IFERROR(D137-E137, "N/A") -> -32 | F139: =IFERROR(E137-F137, "N/A") -> -49.3 | G139: =IFERROR(F137-G137, "N/A") -> -146.8 | H139: =IFERROR(G137-H137, "N/A") -> 17.9 | I139: =IFERROR(H137-I137, "N/A") -> -30.1 | J139: =IFERROR(I137-J137, "N/A") -> 438.7 | K139: =IFERROR(J137-K137, "N/A") -> -423.8 | L139: =IFERROR(K137-L137, "N/A") -> 83.5 | ... AQ139: =IFERROR(AP137-AQ137, "N/A") -> 131.42391
S141: Obs.: | T141: Se a variação do ano 2 para o ano 1 é positiva, significa que no ano 2 a operação utilizou mais caixa. Para facilitar o calculo, invertemos a ordem para já deixar o valor negativo quanto formos usar o CWC
E143: 4Q25 | F143: 2026 | G143: 2027 | H143: 2028 | I143: 2029 | J143: 2030 | K143: 2031
C145: Working Capital | E145: =S137 -> 5607.2182 | F145: =W137 -> 3378.145 | G145: =AA137 -> 4145.3589 | H145: =AE137 -> 5048.6276 | I145: =AI137 -> 6064.4883 | J145: =AM137 -> 6915.0352 | K145: =AQ137 -> 6954.4961
C147: Change in Working Capital | F147: =E145-F145 -> 2229.0732 | G147: =F145-G145 -> -767.2139 | H147: =G145-H145 -> -903.26867 | I147: =H145-I145 -> -1015.8607 | J147: =I145-J145 -> -850.54686 | K147: =J145-K145 -> -39.460912

Sheet P&L Adjusted Pro Forma
C2: P&L Adjusted Pro Forma
B4: Português | C4: English | D4: 1Q22 | E4: 2Q22 | F4: 3Q22 | G4: 4Q22 | H4: 1Q23 | I4: 2Q23 | J4: 3Q23 | K4: 4Q23 | L4: 1Q24 | M4: 2Q24 | N4: 3Q24 | O4: 4Q24 | P4: 1Q25 | Q4: 2Q25 | R4: 3Q25 | S4: 4Q25 | T4: 1Q26 | U4: 2Q26 | V4: 3Q26 | W4: 4Q26 | X4: 1Q27 | Y4: 2Q27 | Z4: 3Q27 | AA4: 4Q27 | AB4: 1Q28 | AC4: 2Q28 | AD4: 3Q28 | AE4: 4Q28 | AF4: 1Q29 | AG4: 2Q29 | AH4: 3Q25 | AI4: 4Q29 | AJ4: 1Q30 | AK4: 2Q30 | AL4: 3Q30 | AM4: 4Q30 | AN4: 1Q31 | AO4: 2Q31 | AP4: 3Q31 | AQ4: 4Q31
B5: Receita Bruta | C5: Gross Revenue | D5: 2271.3 | E5: 2613.5 | F5: 2969.5 | G5: 3306.3 | H5: 2789.9 | I5: 3047.9 | J5: 3274.3 | K5: 3667.3 | L5: 2894.1 | M5: 3370.5 | N5: 3673.5 | O5: 4221.7 | P5: 3311.8 | Q5: 3620 | R5: 3716.2 | S5: ='Revenue per BU and channel'!V73 -> 3856.3271 | T5: ='Revenue per BU and channel'!W73 -> 1995.9347 | U5: ='Revenue per BU and channel'!X73 -> 2098.903 | V5: ='Revenue per BU and channel'!Y73 -> 2207.9466 | W5: ='Revenue per BU and channel'!Z73 -> 2323.2968 | X5: ='Revenue per BU and channel'!AA73 -> 2445.1531 | Y5: ='Revenue per BU and channel'!AB73 -> 2573.6682 | Z5: ='Revenue per BU and channel'!AC73 -> 2708.931 | ... AQ5: ='Revenue per BU and channel'!AT73 -> 4782.9085
B6: Deduções | C6: Deductions | D6: -354.6 | E6: -402.7 | F6: -466.4 | G6: -557 | H6: -492 | I6: -551.2 | J6: -559.6 | K6: -666 | L6: -527 | M6: -601.2 | N6: -635.3 | O6: -817.8 | P6: -615.3 | Q6: -718.6 | R6: -746.4 | S6: =S7*(-S5) -> -683.26756 | T6: =T7*(-T5) -> -353.64153 | U6: =U7*(-U5) -> -371.88556 | V6: =V7*(-V5) -> -391.20599 | W6: =W7*(-W5) -> -411.64385 | X6: =X7*(-X5) -> -433.23445 | Y6: =Y7*(-Y5) -> -456.00488 | Z6: =Z7*(-Z5) -> -479.97086 | ... AQ6: =AQ7*(-AQ5) -> -847.4401
B7: as % of gross revenue | D7: =-D6/D5 -> 0.15612204 | E7: =-E6/E5 -> 0.15408456 | F7: =-F6/F5 -> 0.15706348 | G7: =-G6/G5 -> 0.16846626 | H7: =-H6/H5 -> 0.17635041 | I7: =-I6/I5 -> 0.18084583 | J7: =-J6/J5 -> 0.17090676 | K7: =-K6/K5 -> 0.181605 | ... R7: =-R6/R5 -> 0.20085033 | S7: =AVERAGE(D7:R7) -> 0.17718091 | T7: =S7 -> 0.17718091 | U7: =T7 -> 0.17718091 | V7: =U7 -> 0.17718091 | W7: =V7 -> 0.17718091 | X7: =W7 -> 0.17718091 | Y7: =X7 -> 0.17718091 | Z7: =Y7 -> 0.17718091 | AA7: =Z7 -> 0.17718091 | ... AQ7: =AP7 -> 0.17718091
B9: Receita Líquida | C9: Net Revenue | D9: 1916.7 | E9: 2210.8 | F9: 2503.1 | G9: 2749.3 | H9: 2297.9 | I9: 2496.7 | J9: 2714.7 | K9: 3001.3 | L9: 2367.1 | M9: 2769.3 | N9: 3038.2 | O9: 3403.9 | P9: 2696.5 | Q9: 2901.4 | R9: 2969.8 | S9: =S5+S6 -> 3173.0596 | T9: =T5+T6 -> 1642.2931 | U9: =U5+U6 -> 1727.0175 | V9: =V5+V6 -> 1816.7406 | W9: =W5+W6 -> 1911.653 | X9: =X5+X6 -> 2011.9186 | Y9: =Y5+Y6 -> 2117.6633 | Z9: =Z5+Z6 -> 2228.9601 | ... AQ9: =AQ5+AQ6 -> 3935.4684
B10: Custo da Mercadoria Vendida (CMV) | C10: Cost of Goods Sold (COGS) | D10: -889.6 | E10: -951.9 | F10: -1132.9 | G10: -1282.8 | H10: -1057.9 | I10: -1105.6 | J10: -1226.7 | K10: -1318.1 | L10: -1077.6 | M10: -1214.5 | N10: -1386.7 | O10: -1515.8 | P10: -1219.7 | Q10: -1280.9 | R10: -1345.9 | S10: =-S11*S5 -> -1428.1011 | T10: =-T11*T5 -> -739.14801 | U10: =-U11*U5 -> -777.27995 | V10: =-V11*V5 -> -817.6617 | W10: =-W11*W5 -> -860.37898 | X10: =-X11*X5 -> -905.5056 | Y10: =-Y11*Y5 -> -953.0982 | Z10: =-Z11*Z5 -> -1003.1896 | ... AQ10: =-AQ11*AQ5 -> -1771.239
B11: as % of gross revenue | D11: =-D10/D5 -> 0.39166997 | E11: =-E10/E5 -> 0.36422422 | F11: =-F10/F5 -> 0.38151204 | G11: =-G10/G5 -> 0.38798657 | H11: =-H10/H5 -> 0.37918922 | I11: =-I10/I5 -> 0.36274156 | J11: =-J10/J5 -> 0.37464496 | K11: =-K10/K5 -> 0.35941974 | ... R11: =-R10/R5 -> 0.36217103 | S11: =AVERAGE(D11:R11) -> 0.37032676 | T11: =S11 -> 0.37032676 | U11: =T11 -> 0.37032676 | V11: =U11 -> 0.37032676 | W11: =V11 -> 0.37032676 | X11: =W11 -> 0.37032676 | Y11: =X11 -> 0.37032676 | Z11: =Y11 -> 0.37032676 | AA11: =Z11 -> 0.37032676 | ... AQ11: =AP11 -> 0.37032676
B13: CMV (ex. D&A) | C13: COGS (ex. D&A) | D13: -881.1 | E13: -943.2 | F13: -1123.9 | G13: -1273.4 | H13: -1048.9 | I13: -1096.5 | J13: -1217.7 | K13: -1309.1 | L13: -1068 | M13: -1204.8 | N13: -1376.5 | O13: -1504.5 | P13: -1209.2 | Q13: -1271.2 | R13: -1335.5
B14: CMV (ex. D&A ex. IFRS-16) | C14: COGS (ex. D&A ex. IFRS-16) | D14: -882.3 | E14: -944.4 | F14: -1125.1 | G14: -1274.5 | H14: -1050 | I14: -1097.6 | J14: -1218.9 | K14: -1310 | L14: -1069.3 | M14: -1206.1 | N14: -1377.8 | O14: -1505.8 | P14: -1210.5 | Q14: -1272.5 | R14: -1336.8
B15: Arrendamentos (Impacto IFRS-16) | C15: Leases (IFRS-16 Impact) | D15: 1.2 | E15: 1.2 | F15: 1.2 | G15: 1.1 | H15: 1.1 | I15: 1.1 | J15: 1.2 | K15: 0.9 | L15: 1.3 | M15: 1.3 | N15: 1.3 | O15: 1.3 | P15: 1.3 | Q15: 1.3 | R15: 1.3
B16: Depreciação & Amortização | C16: Depreciation and Amortization | D16: -8.5 | E16: -8.7 | F16: -9 | G16: -9.4 | H16: -9 | I16: -9.1 | J16: -9 | K16: -9 | L16: -9.6 | M16: -9.7 | N16: -10.2 | O16: -11.3 | P16: -10.5 | Q16: -9.7 | R16: -10.4
B17: Lucro Bruto | C17: Gross Profit | D17: 1027.1 | E17: 1258.9 | F17: 1370.2 | G17: 1466.5 | H17: 1240 | I17: 1391.1 | J17: 1488 | K17: 1683.2 | L17: 1289.5 | M17: 1554.8 | N17: 1651.5 | O17: 1888.1 | P17: 1476.8 | Q17: 1620.5 | R17: 1623.9 | S17: =S9+S10 -> 1744.9585 | T17: =T9+T10 -> 903.14513 | U17: =U9+U10 -> 949.73753 | V17: =V9+V10 -> 999.07889 | W17: =W9+W10 -> 1051.274 | X17: =X9+X10 -> 1106.413 | Y17: =Y9+Y10 -> 1164.5651 | Z17: =Z9+Z10 -> 1225.7705 | ... AQ17: =AQ9+AQ10 -> 2164.2294
B18: Despesa Total | C18: Total Expenses | D18: -844.2 | E18: -940.9 | F18: -1045 | G18: -1148.8 | H18: -1009 | I18: -1056.5 | J18: -1154.7 | K18: -1310.1 | L18: -1068.5 | M18: -1197.3 | N18: -1320.5 | O18: -1525.4 | P18: -1200.8 | Q18: -1237.8 | R18: -1303.9 | S18: =S19*-S5 -> -1375.3866 | T18: =T19*-T5 -> -711.86436 | U18: =U19*-U5 -> -748.58877 | V18: =V19*-V5 -> -787.47992 | W18: =W19*-W5 -> -828.62041 | X18: =X19*-X5 -> -872.08131 | Y18: =Y19*-Y5 -> -917.91716 | Z18: =Z19*-Z5 -> -966.15958 | ... AQ18: =AQ19*-AQ5 -> -1705.8585
B19: as % of gross revenue | D19: =-D18/D5 -> 0.37168142 | E19: =-E18/E5 -> 0.36001531 | F19: =-F18/F5 -> 0.3519111 | G19: =-G18/G5 -> 0.34745788 | H19: =-H18/H5 -> 0.36166171 | I19: =-I18/I5 -> 0.34663211 | J19: =-J18/J5 -> 0.35265553 | K19: =-K18/K5 -> 0.3572383 | ... R19: =-R18/R5 -> 0.35086917 | S19: =AVERAGE(D19:R19) -> 0.35665715 | T19: =S19 -> 0.35665715 | U19: =T19 -> 0.35665715 | V19: =U19 -> 0.35665715 | W19: =V19 -> 0.35665715 | X19: =W19 -> 0.35665715 | Y19: =X19 -> 0.35665715 | Z19: =Y19 -> 0.35665715 | AA19: =Z19 -> 0.35665715 | ... AQ19: =AP19 -> 0.35665715
B21: Despesas | C21: Expenses | D21: -773.7 | E21: -865.3 | F21: -959.6 | G21: -1039.2 | H21: -912 | I21: -945.1 | J21: -1039.2 | K21: -1193.5 | L21: -952.1 | M21: -1073 | N21: -1184.8 | O21: -1380.2 | P21: -1059.6 | Q21: -1094.6 | R21: -1157.6
B22: Fixas | C22: Fixed | D22: -344.4 | E22: -377.4 | F22: -408.9 | G22: -436 | H22: -390.6 | I22: -374.2 | J22: -439.2 | K22: -470.3 | L22: -435.7 | M22: -448 | N22: -473.1 | O22: -536.5 | P22: -474.9 | Q22: -453.4 | R22: -464.7
B23: Variáveis | C23: Variable | D23: -377.1 | E23: -406.2 | F23: -456.6 | G23: -556.2 | H23: -452.7 | I23: -473 | J23: -523.2 | K23: -618.8 | L23: -467.8 | M23: -533.8 | N23: -588.5 | O23: -719.6 | P23: -535 | Q23: -569.4 | R23: -590.1
B24: Eventuais | C24: Eventuals | D24: -93.9 | E24: -126.6 | F24: -142.3 | G24: -129.2 | H24: -124.3 | I24: -157.4 | J24: -137.8 | K24: -176.8 | L24: -114.2 | M24: -154 | N24: -189.4 | O24: -199.4 | P24: -117.1 | Q24: -144.7 | R24: -172.2
B25: Arrendamentos (Impacto IFRS-16) | C25: Leases (IFRS-16 Impact) | D25: 41.7 | E25: 44.9 | F25: 48.2 | G25: 82.2 | H25: 55.6 | I25: 59.5 | J25: 61 | K25: 72.4 | L25: 65.6 | M25: 62.8 | N25: 66.2 | O25: 75.3 | P25: 67.4 | Q25: 72.9 | R25: 69.4
B26: Depreciação e Amortização | C26: Depreciation and Amortization | D26: -70.5 | E26: -75.6 | F26: -85.4 | G26: -109.6 | H26: -97 | I26: -111.4 | J26: -115.5 | K26: -116.6 | L26: -116.4 | M26: -124.3 | N26: -135.7 | O26: -145.2 | P26: -141.2 | Q26: -143.2 | R26: -146.3
B27: Perda por Impairment | C27: Impairment losses | D27: 0 | E27: 0 | F27: 0 | G27: 0 | H27: 0 | I27: 0 | J27: 0 | K27: 0 | L27: 0 | M27: 0 | N27: 0 | O27: 0 | P27: 0 | Q27: 0 | R27: 0
B28: EBIT | C28: EBIT | D28: 182.9 | E28: 318 | F28: 325.2 | G28: 317.7 | H28: 231 | I28: 334.6 | J28: 333.3 | K28: 373.1 | L28: 221 | M28: 357.5 | N28: 331 | O28: 362.7 | P28: 276 | Q28: 382.7 | R28: 320 | S28: =S17+S18 -> 369.57183 | T28: =T17+T18 -> 191.28077 | U28: =U17+U18 -> 201.14876 | V28: =V17+V18 -> 211.59897 | W28: =W17+W18 -> 222.65358 | X28: =X17+X18 -> 234.3317 | Y28: =Y17+Y18 -> 246.64797 | Z28: =Z17+Z18 -> 259.6109 | ... AQ28: =AQ17+AQ18 -> 458.37093
B29: Resultado Financeiro | C29: Financial Results | D29: -63.2 | E29: -70.3 | F29: -91.2 | G29: -128.1 | H29: -116.3 | I29: -146 | J29: -124.4 | K29: -144.7 | L29: -143.8 | M29: -151.8 | N29: -159.4 | O29: -156.8 | P29: -157.7 | Q29: -199.5 | R29: -208.7 | S29: =S30*-S5 -> -160.77397 | T29: =T30*-T5 -> -83.212427 | U29: =U30*-U5 -> -87.505277 | V29: =V30*-V5 -> -92.051407 | W29: =W30*-W5 -> -96.860469 | X29: =X30*-X5 -> -101.94077 | Y29: =Y30*-Y5 -> -107.29869 | Z29: =Z30*-Z5 -> -112.93793 | ... AQ29: =AQ30*-AQ5 -> -199.40404
B30: as % of gross revenue | D30: =-D29/D5 -> 0.027825474 | E30: =-E29/E5 -> 0.026898795 | F30: =-F29/F5 -> 0.030712241 | G30: =-G29/G5 -> 0.038744216 | H30: =-H29/H5 -> 0.041686082 | I30: =-I29/I5 -> 0.047901834 | J30: =-J29/J5 -> 0.037992853 | K30: =-K29/K5 -> 0.039456821 | ... R30: =-R29/R5 -> 0.056159518 | S30: =AVERAGE(D30:R30) -> 0.041690957 | T30: =S30 -> 0.041690957 | U30: =T30 -> 0.041690957 | V30: =U30 -> 0.041690957 | W30: =V30 -> 0.041690957 | X30: =W30 -> 0.041690957 | Y30: =X30 -> 0.041690957 | Z30: =Y30 -> 0.041690957 | AA30: =Z30 -> 0.041690957 | ... AQ30: =AP30 -> 0.041690957
B32: EBT | C32: EBT | D32: 119.7 | E32: 247.7 | F32: 234 | G32: 189.6 | H32: 114.7 | I32: 188.6 | J32: 208.9 | K32: 228.4 | L32: 77.2 | M32: 205.7 | N32: 171.6 | O32: 205.9 | P32: 118.3 | Q32: 183.2 | R32: 111.3 | S32: =S28+S29 -> 208.79786 | T32: =T28+T29 -> 108.06834 | U32: =U28+U29 -> 113.64348 | V32: =V28+V29 -> 119.54756 | W32: =W28+W29 -> 125.79311 | X32: =X28+X29 -> 132.39092 | Y32: =Y28+Y29 -> 139.34928 | Z32: =Z28+Z29 -> 146.67298 | ... AQ32: =AQ28+AQ29 -> 258.96689
B33: IRPJ e CSLL | C33: Income Tax and Social Contribution | D33: 8.2 | E33: 22.2 | F33: -3.7 | G33: 30.8 | H33: 39.2 | I33: 48.7 | J33: 20.7 | K33: 34.5 | L33: 24.6 | M33: -49.6 | N33: -7.7 | O33: -37 | P33: -0.6 | Q33: 100.5 | R33: 90 | S33: =-S34*S32 -> -70.991271 | T33: =-T34*T32 -> -36.743236 | U33: =-U34*U32 -> -38.638785 | V33: =-V34*V32 -> -40.646171 | W33: =-W34*W32 -> -42.769658 | X33: =-X34*X32 -> -45.012914 | Y33: =-Y34*Y32 -> -47.378755 | Z33: =-Z34*Z32 -> -49.868812 | ... AQ33: =-AQ34*AQ32 -> -88.048742
B34: as % of gross revenue | S34: 0.34 | T34: =S34 -> 0.34 | U34: =T34 -> 0.34 | V34: =U34 -> 0.34 | W34: =V34 -> 0.34 | X34: =W34 -> 0.34 | Y34: =X34 -> 0.34 | Z34: =Y34 -> 0.34 | AA34: =Z34 -> 0.34 | ... AQ34: =AP34 -> 0.34
B36: Lucro (Prejuízo) | C36: Profit (Loss) | D36: 127.9 | E36: 269.9 | F36: 230.3 | G36: 220.4 | H36: 153.9 | I36: 237.3 | J36: 229.6 | K36: 262.9 | L36: 101.8 | M36: 156.1 | N36: 163.9 | O36: 168.9 | P36: 117.7 | Q36: 283.7 | R36: 201.3 | S36: =S32+S33 -> 137.80658 | T36: =T32+T33 -> 71.325105 | U36: =U32+U33 -> 75.0047 | V36: =V32+V33 -> 78.901391 | W36: =W32+W33 -> 83.023454 | X36: =X32+X33 -> 87.37801 | Y36: =Y32+Y33 -> 91.970524 | Z36: =Z32+Z33 -> 96.804164 | ... AQ36: =AQ32+AQ33 -> 170.91815
B38: Lucro Bruto | C38: Gross Profit | D38: 1027.1 | E38: 1258.9 | F38: 1370.2 | G38: 1466.5 | H38: 1240 | I38: 1391.1 | J38: 1488 | K38: 1683.2 | L38: 1289.5 | M38: 1554.8 | N38: 1651.5 | O38: 1888.1 | P38: 1476.8 | Q38: 1620.5111 | R38: 1623.9
B39: Margem Bruta | C39: Gross Margin | D39: 0.536 | E39: 0.569 | F39: 0.547 | G39: 0.533 | H39: 0.54 | I39: 0.557 | J39: 0.548 | K39: 0.561 | L39: 0.545 | M39: 0.561 | N39: 0.544 | O39: 0.555 | P39: 0.548 | Q39: 0.559 | R39: 0.547
B40: EBITDA | C40: EBITDA | D40: 261.9 | E40: 402.3 | F40: 419.6 | G40: 436.7 | H40: 337 | I40: 455.1 | J40: 457.8 | K40: 498.7 | L40: 347 | M40: 491.5 | N40: 476.9 | O40: 519.2 | P40: 427.7 | Q40: 535.61112 | R40: 476.7
B41: Margem EBITDA | C41: EBITDA Margin | D41: 0.137 | E41: 0.182 | F41: 0.168 | G41: 0.159 | H41: 0.147 | I41: 0.182 | J41: 0.169 | K41: 0.166 | L41: 0.147 | M41: 0.177 | N41: 0.157 | O41: 0.153 | P41: 0.159 | Q41: 0.185 | R41: 0.161
B42: EBITDA (pré IFRS-16) | C42: EBITDA (ex. IFRS-16) | D42: 219 | E42: 356.2 | F42: 370.2 | G42: 353.4 | H42: 280.3 | I42: 394.5 | J42: 395.6 | K42: 425.4 | L42: 280.1 | M42: 427.4 | N42: 409.4 | O42: 442.6 | P42: 359 | Q42: 461.41112 | R42: 406
B43: Margem EBITDA (pré IFRS-16) | C43: EBITDA Margin (ex. IFRS-16) | D43: 0.114 | E43: 0.161 | F43: 0.148 | G43: 0.129 | H43: 0.122 | I43: 0.158 | J43: 0.146 | K43: 0.142 | L43: 0.118 | M43: 0.154 | N43: 0.135 | O43: 0.13 | P43: 0.133 | Q43: 0.159 | R43: 0.137
B44: Lucro Líquido | C44: Net Income | D44: 127.9 | E44: 269.9 | F44: 230.3 | G44: 220.4 | H44: 153.9 | I44: 237.3 | J44: 229.6 | K44: 262.9 | L44: 101.8 | M44: 156.1 | N44: 163.9 | O44: 168.9 | P44: 117.7 | Q44: 283.71112 | R44: 201.3
B45: Margem Líquida | C45: Net Margin | D45: 0.067 | E45: 0.122 | F45: 0.092 | G45: 0.08 | H45: 0.067 | I45: 0.095 | J45: 0.085 | K45: 0.088 | L45: 0.043 | M45: 0.056 | N45: 0.054 | O45: 0.05 | P45: 0.044 | Q45: 0.098 | R45: 0.068 | S45: =S36/S5 -> 0.03573519 | T45: =T36/T5 -> 0.03573519 | U45: =U36/U5 -> 0.03573519 | V45: =V36/V5 -> 0.03573519 | W45: =W36/W5 -> 0.03573519 | X45: =X36/X5 -> 0.03573519 | Y45: =Y36/Y5 -> 0.03573519 | Z45: =Z36/Z5 -> 0.03573519 | ... AQ45: =AQ36/AQ5 -> 0.03573519
D49: 2025 | E49: 2026 | F49: 2027 | G49: 2028 | H49: 2029 | I49: 2030 | J49: 2031
C52: EBIT | E52: =SUM(T28:W28) -> 826.68208 | F52: =SUM(U28:X28) -> 869.73301 | G52: =SUM(V28:Y28) -> 915.23222 | H52: =SUM(W28:Z28) -> 963.24415 | I52: =SUM(X28:AA28) -> 1013.8112 | J52: =SUM(Y28:AB28) -> 1066.9459
C54: Net Revenue | D54: =SUM(P9:S9) -> 11740.76 | E54: =SUM(Q9:T9) -> 10686.553 | F54: =SUM(R9:U9) -> 9512.1702 | G54: =SUM(S9:V9) -> 8359.1108 | H54: =SUM(T9:W9) -> 7097.7042 | I54: =SUM(U9:X9) -> 7467.3296 | J54: =SUM(V9:Y9) -> 7857.9755
C55: EBITDA | D55: =SUM(P28:S28)+CAPEX!D20 -> 1971.8329 | E55: =E52+CAPEX!E20 -> 1531.1821 | F55: =F52+CAPEX!F20 -> 1596.433 | G55: =G52+CAPEX!G20 -> 1664.1322 | H55: =H52+CAPEX!H20 -> 1734.3441 | I55: =I52+CAPEX!I20 -> 1807.1112 | J55: =J52+CAPEX!J20 -> 1882.4459
C56: EBITDA Margin | D56: =D55/D54 -> 0.16794765 | E56: =E55/E54 -> 0.1432812 | F56: =F55/F54 -> 0.16783058 | G56: =G55/G54 -> 0.19908005 | H56: =H55/H54 -> 0.24435284 | I56: =I55/I54 -> 0.24200234 | J56: =J55/J54 -> 0.23955864

Sheet VALUATION
E9: Free Cash Flow to Firm | J9: 2026 | K9: 2027 | L9: 2028 | M9: 2029 | N9: 2030 | O9: 2031
E11: EBIT | J11: =SUM('P&L Adjusted Pro Forma'!T28:W28) -> 826.68208 | K11: =SUM('P&L Adjusted Pro Forma'!U28:X28) -> 869.73301 | L11: =SUM('P&L Adjusted Pro Forma'!V28:Y28) -> 915.23222 | M11: =SUM('P&L Adjusted Pro Forma'!W28:Z28) -> 963.24415 | N11: =SUM('P&L Adjusted Pro Forma'!X28:AA28) -> 1013.8112 | O11: =SUM('P&L Adjusted Pro Forma'!Y28:AB28) -> 1066.9459
E12: Tax Shield | J12: =(1-0.34) -> 0.66 | K12: =J12 -> 0.66 | L12: =K12 -> 0.66 | M12: =L12 -> 0.66 | N12: =M12 -> 0.66 | O12: =N12 -> 0.66
E13: (=) NOPAT | J13: =J11*J12 -> 545.61017 | K13: =K11*K12 -> 574.02379 | L13: =L11*L12 -> 604.05326 | M13: =M11*M12 -> 635.74114 | N13: =N11*N12 -> 669.11541 | O13: =O11*O12 -> 704.18429
E14: (+) D&A | J14: =CAPEX!D20 -> 623.56112 | K14: =CAPEX!E20 -> 704.5 | L14: =CAPEX!F20 -> 726.7 | M14: =CAPEX!G20 -> 748.9 | N14: =CAPEX!H20 -> 771.1 | O14: =CAPEX!I20 -> 793.3
E15: (-) CAPEX | J15: =-CAPEX!D15 -> -487.94106 | K15: =-CAPEX!E15 -> -503.84966 | L15: =-CAPEX!F15 -> -520.36695 | M15: =-CAPEX!G15 -> -537.51789 | N15: =-CAPEX!H15 -> -555.32857 | O15: =-CAPEX!I15 -> -573.82615
E16: (-) Change in Working Capital | J16: =-'Balance Sheet'!F147 -> -2229.0732 | K16: =-'Balance Sheet'!G147 -> 767.2139 | L16: =-'Balance Sheet'!H147 -> 903.26867 | M16: =-'Balance Sheet'!I147 -> 1015.8607 | N16: =-'Balance Sheet'!J147 -> 850.54686 | O16: =-'Balance Sheet'!K147 -> 39.460912
E18: (=) FCFF | J18: =SUM(J13:J16) -> -1547.843 | K18: =SUM(K13:K16) -> 1541.888 | L18: =SUM(L13:L16) -> 1713.655 | M18: =SUM(M13:M16) -> 1862.984 | N18: =SUM(N13:N16) -> 1735.4337 | O18: =SUM(O13:O16) -> 963.11906
E20: Fluxo de Caixa para a Firma a ser Descontado | J20: =J18 -> -1547.843 | K20: =K18 -> 1541.888 | L20: =L18 -> 1713.655 | M20: =M18 -> 1862.984 | N20: =N18 -> 1735.4337 | O20: =O18 -> 963.11906
E21: Valor Terminal | O21: =(O20*(1+G69))/(O24-G69) -> 8545.3593
O22: =P22*'P&L Adjusted Pro Forma'!J55 -> 9412.2295 | P22: 5 | Q22: EBITDA @31
E24: % WACC (R$, nominal) | J24: =$G$67 -> 0.12383374 | K24: =J24 -> 0.12383374 | L24: =K24 -> 0.12383374 | M24: =L24 -> 0.12383374 | N24: =M24 -> 0.12383374 | O24: =N24 -> 0.12383374
E26: Períodos a serem Descontados (Fluxo de Caixa) | I26: 0 | J26: 1 | K26: 2 | L26: 3 | M26: 4 | N26: 5 | O26: 6
E27: Períodos a serem Descontados (Valor Terminal) | O27: 6
E29: VPL dos Fluxos de Caixa para a Firma @2025E, EoP | I29: =SUM(J29:Q29) -> 3664.8095 | J29: =J20*(1/(1+J24)^J26) -> -1377.2882 | K29: =K20*(1/(1+K24)^K26) -> 1220.8117 | L29: =L20*(1/(1+L24)^L26) -> 1207.3055 | M29: =M20*(1/(1+M24)^M26) -> 1167.8871 | N29: =N20*(1/(1+N24)^N26) -> 968.04977 | O29: =O20*(1/(1+O24)^O26) -> 478.04367
E30: VPL do Valor Terminal @2025E, EoP | I30: =O21/(1+O24)^O27 -> 4241.4849
E31: Valor Terminal enquanto % do Valor da Firma | I31: =I30/I34 -> 0.53646938
E34: Valor da Firma | I34: =I29+I30 -> 7906.2944
E35: (-) Dívida Líquida 2025A | I35: =-('Balance Sheet'!R46+'Balance Sheet'!R33) -> -3062.6
E36: (=) Valor do Equity | I36: =I34+I35 -> 4843.6944
E38: EV/EBITDA | G38: x | I38: =I34/'P&L Adjusted Pro Forma'!D55 -> 4.0096167
E39: EV/Receita Líquida | G39: x | I39: =I34/'P&L Adjusted Pro Forma'!D54 -> 0.6734057
E41: Total de ON | I41: 206489813
E42: Price por Share | I42: =(I34*1000000)/I41 -> 38.289029
E44: P/L | I44: =I42/I45 -> 10.676872
E45: Lucro por Ação | I45: {=SUM(('P&L Adjusted Pro Forma'!P36:S36)*1000000)/VALUATION!I41} -> 3.5861652
E47: Preço em 29.01.26 | I47: 27
E48: Upside Prospectivo | I48: =I42/I47-1 -> 0.41811218
Y51: Pag 93: | Z51: https://api.mziq.com/mzfilemanager/v2/d/2edfd667-eaa1-4187-9777-1528284720de/e89d181a-523a-363f-3154-bc922be24581?origin=2
E53: Cost of Capital
E54: WACC Build-Up
E56: Risk-free rate Brazil | G56: 0.1374
E57: NTNB 2029 Spread (Jan/26) | G57: 0.0683
E58: Long-Term Inflation | G58: 0.0585
E59: Beta (β) | G59: =G78 -> 0.27
E60: Risk Premium Brazil (Damodaran, 2025) | G60: 0.0721
E61: Cost of Equity (Ke) via CAPM | G61: =G56+G60*G59 -> 0.156867
E62: Cost of Debt (Kd) | G62: =(14.9+1.17)/100 -> 0.1607
E63: Capital Structure | G63: -
E64: Debt-to-Value | G64: =1-G65 -> 0.65019695
E65: Equity-to-Value | G65: =('Balance Sheet'!R56/('Balance Sheet'!R56+'Balance Sheet'!R67)) -> 0.34980305
E66: Marginal Tax rate | G66: 0.34
E67: Target WACC % | G67: =(G65*G61)+(G64*G62)*(1-G66) -> 0.12383374
E69: Annual Growth Rate in Perpetuity (g) | G69: 0.01
E72: Stock Beta (β)
E74: Investing Pro (5y) | G74: 0.27
E75: Quant Brazil (4 dias atrás) | G75: 1.63
E76: Trading View (1y) | G76: 1.33 | J76: 2016 | K76: 2017 | L76: 2018 | M76: 2019 | N76: 2020 | O76: 2021 | P76: 2022 | Q76: 2023 | R76: 2024 | S76: 2025 | T76: Hoje
E77: Oceans14 | G77: =AVERAGE(J77:T77) -> 1.1463636 | J77: 0.58 | K77: 1.01 | L77: 1 | M77: 0.58 | N77: 0.93 | O77: 0.96 | P77: 1.05 | Q77: 1.64 | R77: 1.62 | S77: 1.61 | T77: 1.63
E78: Yahoo Finance (5Y) | G78: 0.27

Sheet Preço Alvo
J9: Casa de Research | M9: Preço Alvo por ON
J11: BTG | M11: 51
J12: XP | M12: 55
J13: Itaú BBA | M13: 36
J14: UBS | M14: 37
J15: CITI | M15: 28
J16: Empiricus | M16: 41
J20: Média | M20: =AVERAGE(M11:M16) -> 41.333333

Sheet Stores
C2: Stores
B4: Português | C4: English | D4: 1Q22 | E4: 2Q22 | F4: 3Q22 | G4: 4Q22 | H4: 1Q23 | I4: 2Q23 | J4: 3Q23 | K4: 4Q23 | L4: 1Q24 | M4: 2Q24 | N4: 3Q24 | O4: 4Q24 | P4: 1Q25 | Q4: 2Q25 | R4: 3Q25 | U4: CQGR | W4: 4Q25 | X4: 1Q26 | Y4: 2Q26 | Z4: 3Q26 | AA4: 4Q26 | AB4: 1Q27 | AC4: 2Q27 | AD4: 3Q27 | AE4: 4Q27 | AF4: 1Q28 | AG4: 2Q28 | AH4: 3Q28 | AI4: 4Q28 | AJ4: 1Q29 | AK4: 2Q29 | AL4: 3Q25 | AM4: 4Q29 | AN4: 1Q30 | AO4: 2Q30 | AP4: 3Q30 | AQ4: 4Q30 | AR4: 1Q31 | AS4: 2Q31 | AT4: 3Q31 | AU4: 4Q31
B6: Azzas 2154 (Consolidado) | C6: Azzas 2154 (Consolidated) | U6: Lojas/m2 | W6: =W14/W7 -> 0.0097299116 | X6: =X14/X7 -> 0.0096829697 | Y6: =Y14/Y7 -> 0.0096362543 | Z6: =Z14/Z7 -> 0.0095897643 | AA6: =AA14/AA7 -> 0.0095434986 | AB6: =AB14/AB7 -> 0.009497456 | AC6: =AC14/AC7 -> 0.0094516356 | AD6: =AD14/AD7 -> 0.0094060363 | ... AU6: =AU14/AU7 -> 0.0086636559
B7: Área (m²) | C7: Area (sqm) | D7: 190246.19 | E7: 192878.71 | F7: 193838.35 | G7: 199148.05 | H7: 198106.78 | I7: 198884.9 | J7: 199925.68 | K7: 206225.3 | L7: 204180.11 | M7: 206838.53 | N7: 205874.86 | O7: 211108.63 | P7: 209717.37 | Q7: 208451.97 | R7: 207935.27 | U7: =((R7/D7)^(1/15))-1 -> 0.0059447915 | W7: =R7*(1+U$7) -> 209171.4 | X7: =W7*(1+$U$7) -> 210414.88 | Y7: =X7*(1+$U$7) -> 211665.76 | Z7: =Y7*(1+$U$7) -> 212924.06 | AA7: =Z7*(1+$U$7) -> 214189.85 | AB7: =AA7*(1+$U$7) -> 215463.17 | AC7: =AB7*(1+$U$7) -> 216744.05 | AD7: =AC7*(1+$U$7) -> 218032.55 | AE7: =AD7*(1+$U$7) -> 219328.71 | ... AU7: =AT7*(1+$U$7) -> 241146.98
B8: Área (m²) - Continuadas | C8: Area (sqm) - Continued brands | D8: 189301.16 | E8: 191862.33 | F8: 192821.97 | G8: 197690.89 | H8: 196817.67 | I8: 197502.46 | J8: 198594.24 | K8: 204473.32 | L8: 202593.13 | M8: 205120.66 | N8: 204247.57 | O8: 209439.43 | P8: 209013.66 | Q8: 208323.11 | R8: 207935.27
B9: Lojas Próprias | C9: Owned Stores | D9: 71157.76 | E9: 73140.87 | F9: 73884.31 | G9: 76149.23 | H9: 76523.53 | I9: 77878.29 | J9: 78983.72 | K9: 83226.25 | L9: 83200.83 | M9: 85162.6 | N9: 84770.47 | O9: 87793.57 | P9: 87727.54 | Q9: 87889.53 | R9: 87687.91
B10: Franquias | C10: Franchises | D10: 118143.4 | E10: 118721.46 | F10: 118937.66 | G10: 121541.66 | H10: 120294.14 | I10: 119624.17 | J10: 119610.52 | K10: 121247.07 | L10: 119392.3 | M10: 119958.06 | N10: 119477.1 | O10: 121645.86 | P10: 121286.12 | Q10: 120433.58 | R10: 120247.36
B11: Área (m²) - Descontinuadas | C11: Area (sqm) - Discontinued brands | D11: 945.03 | E11: 1016.38 | F11: 1016.38 | G11: 1457.16 | H11: 1289.11 | I11: 1382.44 | J11: 1331.44 | K11: 1751.98 | L11: 1586.98 | M11: 1717.87 | N11: 1627.29 | O11: 1669.2 | P11: 703.71 | Q11: 128.86 | R11: 0
B12: Lojas Próprias - Descontinuadas | C12: Owned Stores | D12: 945.03 | E12: 1016.38 | F12: 1016.38 | G12: 1406.16 | H12: 1238.11 | I12: 1331.44 | J12: 1331.44 | K12: 1743.63 | L12: 1578.63 | M12: 1709.52 | N12: 1627.29 | O12: 1627.29 | P12: 703.71 | Q12: 128.86 | R12: 0
B13: Franquias - Descontinuadas | C13: Franchises | D13: 0 | E13: 0 | F13: 0 | G13: 51 | H13: 51 | I13: 51 | J13: 0 | K13: 8.35 | L13: 8.35 | M13: 8.35 | N13: 0 | O13: 41.91 | P13: 0 | Q13: 0 | R13: 0
B14: Número de Lojas | C14: Number of Stores | D14: 2000 | E14: 2023 | F14: 2032 | G14: 2106 | H14: 2076 | I14: 2071 | J14: 2068 | K14: 2130 | L14: 2091 | M14: 2095 | N14: 2087 | O14: 2129 | P14: 2086 | Q14: 2061 | R14: 2033 | U14: =((R14/D14)^(1/15))-1 -> 0.001091619 | W14: =R14*(1+U14) -> 2035.2193 | X14: =W14*(1+$U$14) -> 2037.4409 | Y14: =X14*(1+$U$14) -> 2039.6651 | Z14: =Y14*(1+$U$14) -> 2041.8916 | AA14: =Z14*(1+$U$14) -> 2044.1206 | AB14: =AA14*(1+$U$14) -> 2046.352 | AC14: =AB14*(1+$U$14) -> 2048.5858 | AD14: =AC14*(1+$U$14) -> 2050.8221 | AE14: =AD14*(1+$U$14) -> 2053.0608 | ... AU14: =AT14*(1+$U$14) -> 2089.2144
B15: Número de Lojas -Continuadas | C15: Number of Stores - Continued brands | D15: 1993 | E15: 2015 | F15: 2024 | G15: 2092 | H15: 2064 | I15: 2058 | J15: 2056 | K15: 2112 | L15: 2074 | M15: 2076 | N15: 2070 | O15: 2111 | P15: 2076 | Q15: 2059 | R15: 2033
B16: Lojas Próprias | C16: Owned Stores | D16: 484 | E16: 502 | F16: 506 | G16: 527 | H16: 524 | I16: 532 | J16: 538 | K16: 565 | L16: 561 | M16: 561 | N16: 562 | O16: 579 | P16: 564 | Q16: 560 | R16: 560
B17: Franquias | C17: Franchises | D17: 1477 | E17: 1481 | F17: 1485 | G17: 1532 | H17: 1507 | I17: 1492 | J17: 1484 | K17: 1514 | L17: 1480 | M17: 1479 | N17: 1471 | O17: 1494 | P17: 1470 | Q17: 1451 | R17: 1424
B18: Internacional | C18: Internacional | D18: 32 | E18: 32 | F18: 33 | G18: 33 | H18: 33 | I18: 34 | J18: 34 | K18: 33 | L18: 33 | M18: 36 | N18: 37 | O18: 38 | P18: 42 | Q18: 48 | R18: 49
B19: Número de Lojas - Descontinuadas | C19: Number of Stores - Discontinued brands | D19: 7 | E19: 8 | F19: 8 | G19: 14 | H19: 12 | I19: 13 | J19: 12 | K19: 18 | L19: 17 | M19: 19 | N19: 17 | O19: 18 | P19: 10 | Q19: 2 | R19: 0
B20: Lojas Próprias | C20: Owned Stores | D20: 7 | E20: 8 | F20: 8 | G20: 13 | H20: 11 | I20: 12 | J20: 12 | K20: 17 | L20: 16 | M20: 18 | N20: 17 | O20: 17 | P20: 10 | Q20: 2 | R20: 0
B21: Franquias | C21: Franchises | D21: 0 | E21: 0 | F21: 0 | G21: 1 | H21: 1 | I21: 1 | J21: 0 | K21: 1 | L21: 1 | M21: 1 | N21: 0 | O21: 1 | P21: 0 | Q21: 0 | R21: 0
B23: Shoes & Bags | C23: Shoes & Bags | U23: Lojas/m2 | W23: =W31/W24 -> 0.018305332 | X23: =X31/X24 -> 0.018317541 | Y23: =Y31/Y24 -> 0.018329757 | Z23: =Z31/Z24 -> 0.018341982 | AA23: =AA31/AA24 -> 0.018354215 | AB23: =AB31/AB24 -> 0.018366456 | AC23: =AC31/AC24 -> 0.018378705 | AD23: =AD31/AD24 -> 0.018390963 | ... AU23: =AU31/AU24 -> 0.018600594
B24: Área (m²) | C24: Area (sqm) | D24: 43288.37 | E24: 44033.89 | F24: 44112.07 | G24: 44840.34 | H24: 44566.17 | I24: 45222.2 | J24: 45068.37 | K24: 46162.16 | L24: 45619.44 | M24: 45750.35 | N24: 45719.16 | O24: 47019.12 | P24: 45843.4 | Q24: 45576.72 | R24: 45481.55 | U24: =((R24/D24)^(1/15))-1 -> 0.0033002834 | W24: =R24*(1+U24) -> 45631.652 | X24: =W24*(1+$U$24) -> 45782.249 | Y24: =X24*(1+$U$24) -> 45933.344 | Z24: =Y24*(1+$U$24) -> 46084.937 | AA24: =Z24*(1+$U$24) -> 46237.03 | AB24: =AA24*(1+$U$24) -> 46389.625 | AC24: =AB24*(1+$U$24) -> 46542.724 | AD24: =AC24*(1+$U$24) -> 46696.329 | AE24: =AD24*(1+$U$24) -> 46850.44 | ... AU24: =AT24*(1+$U$24) -> 49386.543
B25: Área (m²) - Continuadas | C25: Area (sqm) - Continued brands | D25: 42804.55 | E25: 43550.07 | F25: 43628.25 | G25: 44305.52 | H25: 44199.4 | I25: 44855.43 | J25: 44752.6 | K25: 45838.04 | L25: 45295.32 | M25: 45426.23 | N25: 45403.39 | O25: 46703.35 | P25: 45843.4 | Q25: 45576.72 | R25: 45481.55
B26: Lojas Próprias | C26: Owned Stores | D26: 5815.6 | E26: 6358.83 | F26: 6385.29 | G26: 6574.14 | H26: 6825.54 | I26: 7577.83 | J26: 7266.65 | K26: 7427.17 | L26: 7404.22 | M26: 7429.45 | N26: 7520.87 | O26: 7837.87 | P26: 7353.1 | Q26: 7239.31 | R26: 7203.62
B27: Franquias | C27: Franchises | D27: 36988.95 | E27: 37191.24 | F27: 37242.96 | G27: 37731.38 | H27: 37373.86 | I27: 37277.6 | J27: 37485.95 | K27: 38410.87 | L27: 37891.1 | M27: 37996.78 | N27: 37882.52 | O27: 38865.48 | P27: 38490.3 | Q27: 38337.41 | R27: 38277.93
B28: Área (m²) - Descontinuadas | C28: Area (sqm) - Discontinued brands | D28: 483.82 | E28: 483.82 | F28: 483.82 | G28: 534.82 | H28: 366.77 | I28: 366.77 | J28: 315.77 | K28: 324.12 | L28: 324.12 | M28: 324.12 | N28: 315.77 | O28: 315.77 | P28: 0 | Q28: 0 | R28: 0
B29: Lojas Próprias - Descontinuadas | C29: Owned Stores | D29: 483.82 | E29: 483.82 | F29: 483.82 | G29: 483.82 | H29: 315.77 | I29: 315.77 | J29: 315.77 | K29: 315.77 | L29: 315.77 | M29: 315.77 | N29: 315.77 | O29: 315.77 | P29: 0 | Q29: 0 | R29: 0
B30: Franquias - Descontinuadas | C30: Franchises | D30: 0 | E30: 0 | F30: 0 | G30: 51 | H30: 51 | I30: 51 | J30: 0 | K30: 8.35 | L30: 8.35 | M30: 8.35 | N30: 0 | O30: 0 | P30: 0 | Q30: 0 | R30: 0
B31: Número de Lojas | C31: Number of Stores | D31: 784 | E31: 797 | F31: 804 | G31: 829 | H31: 821 | I31: 820 | J31: 817 | K31: 848 | L31: 833 | M31: 843 | N31: 840 | O31: 863 | P31: 846 | Q31: 841 | R31: 832 | U31: =((R31/D31)^(1/15))-1 -> 0.0039694187 | W31: =R31*(1+U31) -> 835.30256 | X31: =W31*(1+$U$31) -> 838.61822 | Y31: =X31*(1+$U$31) -> 841.94705 | Z31: =Y31*(1+$U$31) -> 845.28909 | AA31: =Z31*(1+$U$31) -> 848.6444 | AB31: =AA31*(1+$U$31) -> 852.01302 | AC31: =AB31*(1+$U$31) -> 855.39502 | AD31: =AC31*(1+$U$31) -> 858.79044 | AE31: =AD31*(1+$U$31) -> 862.19934 | ... AU31: =AT31*(1+$U$31) -> 918.61902
B32: Número de Lojas -Continuadas | C32: Number of Stores - Continued brands | D32: 780 | E32: 793 | F32: 800 | G32: 824 | H32: 818 | I32: 817 | J32: 815 | K32: 845 | L32: 830 | M32: 840 | N32: 838 | O32: 861 | P32: 846 | Q32: 841 | R32: 832
B33: Lojas Próprias | C33: Owned Stores | D33: 60 | E33: 68 | F33: 69 | G33: 72 | H33: 72 | I33: 78 | J33: 75 | K33: 81 | L33: 79 | M33: 82 | N33: 82 | O33: 83 | P33: 77 | Q33: 75 | R33: 74
B34: Arezzo | C34: Arezzo | D34: 17 | E34: 18 | F34: 18 | G34: 18 | H34: 17 | I34: 23 | J34: 22 | K34: 24 | L34: 23 | M34: 24 | N34: 24 | O34: 24 | P34: 21 | Q34: 20 | R34: 20
B35: Schutz | C35: Schutz | D35: 20 | E35: 22 | F35: 22 | G35: 22 | H35: 22 | I35: 21 | J35: 20 | K35: 20 | L35: 19 | M35: 19 | N35: 19 | O35: 19 | P35: 16 | Q35: 16 | R35: 16
B36: Alexandre Birman | C36: Alexandre Birman | D36: 8 | E36: 10 | F36: 11 | G36: 12 | H36: 12 | I36: 11 | J36: 11 | K36: 13 | L36: 13 | M36: 13 | N36: 13 | O36: 13 | P36: 13 | Q36: 13 | R36: 13
B37: Anacapri | C37: Anacapri | D37: 2 | E37: 2 | F37: 2 | G37: 2 | H37: 2 | I37: 2 | J37: 2 | K37: 2 | L37: 2 | M37: 2 | N37: 2 | O37: 2 | P37: 2 | Q37: 2 | R37: 2
B38: Vans | C38: Vans | D38: 13 | E38: 16 | F38: 16 | G38: 18 | H38: 18 | I38: 20 | J38: 20 | K38: 21 | L38: 21 | M38: 23 | N38: 23 | O38: 24 | P38: 24 | Q38: 23 | R38: 22
B39: Vicenza | C39: Vicenza | D39: 0 | E39: 0 | F39: 0 | G39: 0 | H39: 1 | I39: 1 | J39: - | K39: 1 | L39: 1 | M39: 1 | N39: 1 | O39: 1 | P39: 1 | Q39: 1 | R39: 1
B40: Franquias | C40: Franchises | D40: 709 | E40: 714 | F40: 720 | G40: 741 | H40: 735 | I40: 727 | J40: 728 | K40: 754 | L40: 741 | M40: 748 | N40: 746 | O40: 768 | P40: 758 | Q40: 751 | R40: 743
B41: Arezzo | C41: Arezzo | D41: 431 | E41: 430 | F41: 431 | G41: 439 | H41: 430 | I41: 421 | J41: 417 | K41: 421 | L41: 416 | M41: 418 | N41: 419 | O41: 421 | P41: 415 | Q41: 412 | R41: 406
B42: Schutz | C42: Schutz | D42: 62 | E42: 62 | F42: 62 | G42: 62 | H42: 61 | I42: 60 | J42: 61 | K42: 61 | L42: 58 | M42: 56 | N42: 53 | O42: 54 | P42: 54 | Q42: 52 | R42: 50
B43: Anacapri | C43: Anacapri | D43: 204 | E43: 210 | F43: 215 | G43: 226 | H43: 229 | I43: 230 | J43: 233 | K43: 252 | L43: 247 | M43: 253 | N43: 253 | O43: 266 | P43: 262 | Q43: 260 | R43: 256
B44: Vans | C44: Vans | D44: 12 | E44: 12 | F44: 12 | G44: 14 | H44: 15 | I44: 16 | J44: 17 | K44: 20 | L44: 20 | M44: 21 | N44: 21 | O44: 27 | P44: 27 | Q44: 27 | R44: 31
B45: Internacional | C45: Internacional | D45: 11 | E45: 11 | F45: 11 | G45: 11 | H45: 11 | I45: 12 | J45: 12 | K45: 10 | L45: 10 | M45: 10 | N45: 10 | O45: 10 | P45: 11 | Q45: 15 | R45: 15
B46: Lojas Próprias | C46: Owned Stores | D46: 5 | E46: 5 | F46: 5 | G46: 5 | H46: 5 | I46: 6 | J46: 6 | K46: 4 | L46: 4 | M46: 4 | N46: 4 | O46: 4 | P46: 5 | Q46: 5 | R46: 5
B47: Franquias | C47: Franchises | D47: 6 | E47: 6 | F47: 6 | G47: 6 | H47: 6 | I47: 6 | J47: 6 | K47: 6 | L47: 6 | M47: 6 | N47: 6 | O47: 6 | P47: 6 | Q47: 10 | R47: 10
B48: Número de Lojas - Descontinuadas | C48: Number of Stores - Discontinued brands | D48: 4 | E48: 4 | F48: 4 | G48: 5 | H48: 3 | I48: 3 | J48: 2 | K48: 3 | L48: 3 | M48: 3 | N48: 2 | O48: 2 | P48: 0 | Q48: 0 | R48: 0
B49: Lojas Próprias | C49: Owned Stores | D49: 4 | E49: 4 | F49: 4 | G49: 4 | H49: 2 | I49: 2 | J49: 2 | K49: 2 | L49: 2 | M49: 2 | N49: 2 | O49: 2 | P49: 0 | Q49: 0 | R49: 0
B50: Franquias | C50: Franchises | D50: 0 | E50: 0 | F50: 0 | G50: 1 | H50: 1 | I50: 1 | J50: 0 | K50: 1 | L50: 1 | M50: 1 | N50: 0 | O50: 0 | P50: 0 | Q50: 0 | R50: 0
B52: Fashion Women | C52: Fashion Women | D52: 1Q22 | E52: 2Q22 | F52: 3Q22 | G52: 4Q22 | H52: 1Q23 | I52: 2Q23 | J52: 3Q23 | K52: 4Q23 | L52: 1Q24 | M52: 2Q24 | N52: 3Q24 | O52: 4Q24 | P52: 1Q25 | Q52: 2Q25 | R52: 3Q25 | U52: Lojas/m2 | W52: =W56/W53 -> 0.0062713098 | X52: =X56/X53 -> 0.0062478941 | Y52: =Y56/Y53 -> 0.0062245659 | Z52: =Z56/Z53 -> 0.0062013248 | AA52: =AA56/AA53 -> 0.0061781705 | AB52: =AB56/AB53 -> 0.0061551026 | AC52: =AC56/AC53 -> 0.0061321209 | AD52: =AD56/AD53 -> 0.006109225 | ... AU52: =AU56/AU53 -> 0.005732817
B53: Área (m²) | C53: Area (sqm) | D53: 40551.98 | E53: 41139.86 | F53: 41217.16 | G53: 43137.8 | H53: 42607.13 | I53: 42446.46 | J53: 43388.33 | K53: 46347.24 | L53: 45860.24 | M53: 47124.84 | N53: 46415.3 | O53: 48056.93 | P53: 47275.52 | Q53: 47718.52 | R53: 48452.59 | U53: =((R53/D53)^(1/15))-1 -> 0.011937435 | W53: =R53*(1+U53) -> 49030.99 | X53: =W53*(1+$U$53) -> 49616.294 | Y53: =X53*(1+$U$53) -> 50208.585 | Z53: =Y53*(1+$U$53) -> 50807.947 | AA53: =Z53*(1+$U$53) -> 51414.463 | AB53: =AA53*(1+$U$53) -> 52028.22 | AC53: =AB53*(1+$U$53) -> 52649.304 | AD53: =AC53*(1+$U$53) -> 53277.801 | AE53: =AD53*(1+$U$53) -> 53913.802 | ... AU53: =AT53*(1+$U$53) -> 65186.633
B54: Lojas Próprias | C54: Owned Stores | D54: 39347.38 | E54: 39934.86 | F54: 39860.16 | G54: 41848.8 | H54: 41318.13 | I54: 41157.86 | J54: 42099.73 | K54: 45138.24 | L54: 44914.24 | M54: 46243.84 | N54: 45621.68 | O54: 47061.31 | P54: 46279.9 | Q54: 46722.9 | R54: 47731.59
B55: Franquias | C55: Franchises | D55: 1204.6 | E55: 1205 | F55: 1357 | G55: 1289 | H55: 1289 | I55: 1288.6 | J55: 1288.6 | K55: 1209 | L55: 946 | M55: 881 | N55: 793.62 | O55: 995.62 | P55: 995.62 | Q55: 995.62 | R55: 721
B56: Número de Lojas | C56: Number of Stores | D56: 270 | E56: 273 | F56: 274 | G56: 281 | H56: 279 | I56: 280 | J56: 287 | K56: 301 | L56: 294 | M56: 293 | N56: 292 | O56: 302 | P56: 301 | Q56: 302 | R56: 305 | U56: =((R56/D56)^(1/15))-1 -> 0.0081590933 | W56: =R56*(1+U56) -> 307.48852 | X56: =W56*(1+$U$56) -> 309.99735 | Y56: =X56*(1+$U$56) -> 312.52665 | Z56: =Y56*(1+$U$56) -> 315.07658 | AA56: =Z56*(1+$U$56) -> 317.64732 | AB56: =AA56*(1+$U$56) -> 320.23904 | AC56: =AB56*(1+$U$56) -> 322.8519 | AD56: =AC56*(1+$U$56) -> 325.48607 | AE56: =AD56*(1+$U$56) -> 328.14175 | ... AU56: =AT56*(1+$U$56) -> 373.70304
B57: Lojas Próprias | C57: Owned Stores | D57: 248 | E57: 251 | F57: 250 | G57: 258 | H57: 256 | I57: 257 | J57: 264 | K57: 278 | L57: 275 | M57: 272 | N57: 272 | O57: 282 | P57: 278 | Q57: 277 | R57: 283
B58: Animale | C58: Animale | D58: 69 | E58: 68 | F58: 67 | G58: 68 | H58: 67 | I58: 69 | J58: 69 | K58: 70 | L58: 68 | M58: 64 | N58: 64 | O58: 64 | P58: 63 | Q58: 62 | R58: 60
B59: Carol Bassi | C59: Carol Bassi | D59: 2 | E59: 2 | F59: 2 | G59: 5 | H59: 4 | I59: 3 | J59: 4 | K59: 7 | L59: 7 | M59: 8 | N59: 7 | O59: 7 | P59: 7 | Q59: 7 | R59: 9
B60: Cris Barros | C60: Cris Barros | D60: 11 | E60: 11 | F60: 12 | G60: 10 | H60: 10 | I60: 10 | J60: 10 | K60: 10 | L60: 11 | M60: 11 | N60: 11 | O60: 12 | P60: 12 | Q60: 13 | R60: 13
B61: Fábula | C61: Fábula | D61: 18 | E61: 18 | F61: 21 | G61: 21 | H61: 21 | I61: 21 | J61: 21 | K61: 20 | L61: 19 | M61: 18 | N61: 16 | O61: 15 | P61: 10 | Q61: 10 | R61: 10
B62: Farm | C62: Farm | D62: 84 | E62: 86 | F62: 86 | G62: 89 | H62: 89 | I62: 89 | J62: 96 | K62: 104 | L62: 106 | M62: 106 | N62: 108 | O62: 112 | P62: 114 | Q62: 114 | R62: 118
B63: Farm ETC | C63: Farm ETC | D63: 0 | E63: 0 | F63: 0 | G63: 0 | H63: 0 | I63: 0 | J63: 0 | K63: 0 | L63: 0 | M63: 0 | N63: 0 | O63: 0 | P63: 0 | Q63: 0 | R63: 3
B64: Maria Filó | C64: Maria Filó | D64: 40 | E64: 40 | F64: 36 | G64: 36 | H64: 36 | I64: 36 | J64: 35 | K64: 36 | L64: 33 | M64: 33 | N64: 34 | O64: 36 | P64: 36 | Q64: 36 | R64: 35
B65: NV | C65: NV | D65: 11 | E65: 13 | F65: 13 | G65: 16 | H65: 16 | I65: 16 | J65: 17 | K65: 19 | L65: 19 | M65: 19 | N65: 19 | O65: 23 | P65: 23 | Q65: 23 | R65: 23
B66: Off Premium | C66: Off Premium | D66: 13 | E66: 13 | F66: 13 | G66: 13 | H66: 13 | I66: 13 | J66: 12 | K66: 12 | L66: 12 | M66: 13 | N66: 13 | O66: 13 | P66: 13 | Q66: 12 | R66: 12
B67: Franquias | C67: Franchises | D67: 20 | E67: 20 | F67: 21 | G67: 20 | H67: 20 | I67: 20 | J67: 20 | K67: 19 | L67: 15 | M67: 14 | N67: 12 | O67: 12 | P67: 12 | Q67: 12 | R67: 9
B68: Maria Filó | C68: Maria Filó | D68: 20 | E68: 20 | F68: 21 | G68: 20 | H68: 20 | I68: 20 | J68: 20 | K68: 19 | L68: 15 | M68: 14 | N68: 12 | O68: 12 | P68: 12 | Q68: 12 | R68: 9
... B71: Farm Rio (franquias) | C71: Farm Global (franchise) | D71: 0 | E71: 0 | F71: 0 | G71: 0 | H71: 0 | I71: 0 | J71: 0 | K71: 0 | L71: 0 | M71: 1 | N71: 2 | O71: 2 | P71: 2 | Q71: 2 | R71: 2
B73: Fashion Men | C73: Fashion Men | D73: 1Q22 | E73: 2Q22 | F73: 3Q22 | G73: 4Q22 | H73: 1Q23 | I73: 2Q23 | J73: 3Q23 | K73: 4Q23 | L73: 1Q24 | M73: 2Q24 | N73: 3Q24 | O73: 4Q24 | P73: 1Q25 | Q73: 2Q25 | R73: 3Q25 | U73: Lojas/m2 | W73: =W81/W74 -> 0.010987579 | X73: =X81/X74 -> 0.010963785 | Y73: =Y81/Y74 -> 0.010940043 | Z73: =Z81/Z74 -> 0.010916353 | AA73: =AA81/AA74 -> 0.010892714 | AB73: =AB81/AB74 -> 0.010869126 | AC73: =AC81/AC74 -> 0.010845589 | AD73: =AD81/AD74 -> 0.010822103 | ... AU73: =AU81/AU74 -> 0.010430533
B74: Área (m²) | C74: Area (sqm) | D74: 14329.2 | E74: 15192.37 | F74: 15702.16 | G74: 17632.91 | H74: 17718.48 | I74: 18121.5 | J74: 18359.98 | K74: 20005.7 | L74: 20176.73 | M74: 20527.34 | N74: 20957.67 | O74: 21730.98 | P74: 22810.36 | Q74: 22267.73 | R74: 22431.25 | U74: =((R74/D74)^(1/15))-1 -> 0.030327841 | W74: =R74*(1+U74) -> 23111.541 | X74: =W74*(1+$U$74) -> 23812.465 | Y74: =X74*(1+$U$74) -> 24534.645 | Z74: =Y74*(1+$U$74) -> 25278.728 | AA74: =Z74*(1+$U$74) -> 26045.377 | AB74: =AA74*(1+$U$74) -> 26835.277 | AC74: =AB74*(1+$U$74) -> 27649.133 | AD74: =AC74*(1+$U$74) -> 28487.672 | AE74: =AD74*(1+$U$74) -> 29351.642 | ... AU74: =AT74*(1+$U$74) -> 47341.211
B75: Área (m²) - Continuadas | C75: Area (sqm) - Continued brands | D75: 14020.79 | E75: 14812.61 | F75: 15322.4 | G75: 16916.07 | H75: 17001.64 | I75: 17311.33 | J75: 17549.81 | K75: 18783.34 | L75: 19119.37 | M75: 19339.09 | N75: 19769.42 | O75: 20500.82 | P75: 22177.22 | Q75: 22209.44 | R75: 22431.25
B76: Lojas Próprias | C76: Owned Stores | D76: 9960.94 | E76: 10406.07 | F76: 10853.86 | G76: 11636.79 | H76: 11722.36 | I76: 11967.36 | J76: 12142.84 | K76: 12768.14 | L76: 12989.67 | M76: 13076.81 | N76: 13216.07 | O76: 13830.85 | P76: 15140 | Q76: 15135.89 | R76: 15357.7
B77: Franquias | C77: Franchises | D77: 4059.85 | E77: 4406.54 | F77: 4468.54 | G77: 5279.28 | H77: 5279.28 | I77: 5343.97 | J77: 5406.97 | K77: 6015.2 | L77: 6129.7 | M77: 6262.28 | N77: 6553.35 | O77: 6669.97 | P77: 7037.22 | Q77: 7073.55 | R77: 7073.55
B78: Área (m²) - Descontinuadas | C78: Area (sqm) - Discontinued brands | D78: 308.41 | E78: 379.76 | F78: 379.76 | G78: 716.84 | H78: 716.84 | I78: 810.17 | J78: 810.17 | K78: 1222.36 | L78: 1057.36 | M78: 1188.25 | N78: 1188.25 | O78: 1230.16 | P78: 633.14 | Q78: 58.29 | R78: 0
B79: Lojas Próprias - Descontinuadas | C79: Owned Stores | D79: 308.41 | E79: 379.76 | F79: 379.76 | G79: 716.84 | H79: 716.84 | I79: 810.17 | J79: 810.17 | K79: 1222.36 | L79: 1057.36 | M79: 1188.25 | N79: 1188.25 | O79: 1188.25 | P79: 633.14 | Q79: 58.29 | R79: 0
B80: Franquias - Descontinuadas | C80: Franchises | D80: 0 | E80: 0 | F80: 0 | G80: 0 | H80: 0 | I80: 0 | J80: 0 | K80: 0 | L80: 0 | M80: 0 | N80: 0 | O80: 41.91 | P80: 0 | Q80: 0 | R80: 0
B81: Número de Lojas | C81: Number of Stores | D81: 163 | E81: 176 | F81: 182 | G81: 208 | H81: 209 | I81: 213 | J81: 216 | K81: 239 | L81: 241 | M81: 245 | N81: 249 | O81: 261 | P81: 253 | Q81: 246 | R81: 247 | U81: =((R81/D81)^(1/15))-1 -> 0.02809668 | W81: =R81*(1+U81) -> 253.93988 | X81: =W81*(1+$U$81) -> 261.07475 | Y81: =X81*(1+$U$81) -> 268.41008 | Z81: =Y81*(1+$U$81) -> 275.95151 | AA81: =Z81*(1+$U$81) -> 283.70483 | AB81: =AA81*(1+$U$81) -> 291.676 | AC81: =AB81*(1+$U$81) -> 299.87113 | AD81: =AC81*(1+$U$81) -> 308.29651 | AE81: =AD81*(1+$U$81) -> 316.95862 | ... AU81: =AT81*(1+$U$81) -> 493.79407
B82: Número de Lojas - Continuadas | C82: Number of Stores - Continued brands | D82: 162 | E82: 174 | F82: 180 | G82: 202 | H82: 203 | I82: 206 | J82: 209 | K82: 227 | L82: 230 | M82: 232 | N82: 236 | O82: 248 | P82: 244 | Q82: 245 | R82: 247
B83: Lojas Próprias | C83: Owned Stores | D83: 105 | E83: 112 | F83: 117 | G83: 127 | H83: 128 | I83: 129 | J83: 131 | K83: 138 | L83: 139 | M83: 139 | N83: 140 | O83: 147 | P83: 142 | Q83: 142 | R83: 144
B84: Reserva | C84: Reserva | D84: 73 | E84: 79 | F84: 82 | G84: 85 | H84: 85 | I84: 84 | J84: 84 | K84: 87 | L84: 87 | M84: 87 | N84: 87 | O84: 89 | P84: 84 | Q84: 84 | R84: 85
B85: Oficina | C85: Oficina | D85: 8 | E85: 8 | F85: 10 | G85: 13 | H85: 14 | I85: 14 | J85: 15 | K85: 19 | L85: 20 | M85: 20 | N85: 21 | O85: 27 | P85: 29 | Q85: 29 | R85: 30
B86: Foxton | C86: Foxton | D86: 24 | E86: 25 | F86: 25 | G86: 29 | H86: 29 | I86: 31 | J86: 32 | K86: 32 | L86: 32 | M86: 32 | N86: 32 | O86: 31 | P86: 29 | Q86: 29 | R86: 29
B87: Franquias | C87: Franchises | D87: 57 | E87: 62 | F87: 63 | G87: 75 | H87: 75 | I87: 77 | J87: 78 | K87: 89 | L87: 91 | M87: 93 | N87: 96 | O87: 101 | P87: 102 | Q87: 103 | R87: 103
B88: Reserva | C88: Reserva | D88: 57 | E88: 62 | F88: 63 | G88: 75 | H88: 75 | I88: 77 | J88: 78 | K88: 89 | L88: 91 | M88: 93 | N88: 96 | O88: 101 | P88: 102 | Q88: 103 | R88: 103
B89: Número de Lojas - Descontinuadas | C89: Number of Stores - Discontinued brands | D89: 1 | E89: 2 | F89: 2 | G89: 6 | H89: 6 | I89: 7 | J89: 7 | K89: 12 | L89: 11 | M89: 13 | N89: 13 | O89: 13 | P89: 9 | Q89: 1 | R89: 0
B90: Lojas Próprias | C90: Owned Stores | D90: 1 | E90: 2 | F90: 2 | G90: 6 | H90: 6 | I90: 7 | J90: 7 | K90: 12 | L90: 11 | M90: 13 | N90: 13 | O90: 13 | P90: 9 | Q90: 1 | R90: 0
B91: Franquias | C91: Franchises | D91: 0 | E91: 0 | F91: 0 | G91: 0 | H91: 0 | I91: 0 | J91: 0 | K91: 0 | L91: 0 | M91: 0 | N91: 0 | O91: 1 | P91: 0 | Q91: 0 | R91: 0
B93: Basic | C93: Basic | D93: 1Q22 | E93: 2Q22 | F93: 3Q22 | G93: 4Q22 | H93: 1Q23 | I93: 2Q23 | J93: 3Q23 | K93: 4Q23 | L93: 1Q24 | M93: 2Q24 | N93: 3Q24 | O93: 4Q24 | P93: 1Q25 | Q93: 2Q25 | R93: 3Q25 | U93: Lojas/m2 | W93: =W100/W94 -> 0.0070019235 | X93: =X100/X94 -> 0.0069173967 | Y93: =Y100/Y94 -> 0.0068338902 | Z93: =Z100/Z94 -> 0.0067513918 | AA93: =AA100/AA94 -> 0.0066698894 | AB93: =AB100/AB94 -> 0.0065893708 | AC93: =AC100/AC94 -> 0.0065098242 | AD93: =AD100/AD94 -> 0.006431238 | ... AU93: =AU100/AU94 -> 0.0052314847
B94: Área (m²) | C94: Area (sqm) | D94: 92076.64 | E94: 92512.591 | F94: 92806.961 | G94: 93537 | H94: 93215 | I94: 93094.74 | J94: 93109 | K94: 93710.2 | L94: 92523.7 | M94: 93436 | N94: 92782.73 | O94: 94301.601 | P94: 93788.091 | Q94: 92889 | R94: 91569.881 | U94: =((R94/D94)^(1/15))-1 -> -0.00036785674 | W94: =R94*(1+U94) -> 91536.196 | X94: =W94*(1+$U$94) -> 91502.524 | Y94: =X94*(1+$U$94) -> 91468.864 | Z94: =Y94*(1+$U$94) -> 91435.217 | AA94: =Z94*(1+$U$94) -> 91401.582 | AB94: =AA94*(1+$U$94) -> 91367.959 | AC94: =AB94*(1+$U$94) -> 91334.349 | AD94: =AC94*(1+$U$94) -> 91300.751 | AE94: =AD94*(1+$U$94) -> 91267.165 | ... AU94: =AT94*(1+$U$94) -> 90731.473
B95: Área (m²) - Continuadas | C95: Area (sqm) - Continued brands | D95: 91923.84 | E95: 92359.791 | F95: 92654.161 | G95: 93331.5 | H95: 93009.5 | I95: 92889.24 | J95: 92903.5 | K95: 93504.7 | L95: 92318.2 | M95: 93230.5 | N95: 92659.46 | O95: 94178.331 | P95: 93717.521 | Q95: 92818.43 | R95: 91569.881
B96: Lojas Próprias | C96: Owned Stores | D96: 16033.84 | E96: 16441.11 | F96: 16785 | G96: 16089.5 | H96: 16657.5 | I96: 17175.24 | J96: 17474.5 | K96: 17892.7 | L96: 17892.7 | M96: 18412.5 | N96: 18411.85 | O96: 19063.54 | P96: 18954.54 | Q96: 18791.43 | R96: 17395
B97: Franquias | C97: Franchises | D97: 75890 | E97: 75918.681 | F97: 75869.161 | G97: 77242 | H97: 76352 | I97: 75714 | J97: 75429 | K97: 75612 | L97: 74425.5 | M97: 74818 | N97: 74247.61 | O97: 75114.791 | P97: 74762.981 | Q97: 74027 | R97: 74174.881
B98: Área (m²) - Descontinuadas | C98: Area (sqm) - Discontinued brands | D98: 152.8 | E98: 152.8 | F98: 152.8 | G98: 205.5 | H98: 205.5 | I98: 205.5 | J98: 205.5 | K98: 205.5 | L98: 205.5 | M98: 205.5 | N98: 123.27 | O98: 123.27 | P98: 70.57 | Q98: 70.57 | R98: 0
B99: Lojas Próprias - Descontinuadas | C99: Owned Stores | D99: 152.8 | E99: 152.8 | F99: 152.8 | G99: 205.5 | H99: 205.5 | I99: 205.5 | J99: 205.5 | K99: 205.5 | L99: 205.5 | M99: 205.5 | N99: 123.27 | O99: 123.27 | P99: 70.57 | Q99: 70.57 | R99: 0
B100: Número de Lojas | C100: Number of Stores | D100: 783 | E100: 777 | F100: 772 | G100: 788 | H100: 767 | I100: 758 | J100: 748 | K100: 742 | L100: 723 | M100: 714 | N100: 706 | O100: 702 | P100: 686 | Q100: 672 | R100: 649 | U100: =((R100/D100)^(1/15))-1 -> -0.012435366 | W100: =R100*(1+U100) -> 640.92945 | X100: =W100*(1+$U$100) -> 632.95926 | Y100: =X100*(1+$U$100) -> 625.08818 | Z100: =Y100*(1+$U$100) -> 617.31498 | AA100: =Z100*(1+$U$100) -> 609.63844 | AB100: =AA100*(1+$U$100) -> 602.05736 | AC100: =AB100*(1+$U$100) -> 594.57056 | AD100: =AC100*(1+$U$100) -> 587.17686 | AE100: =AD100*(1+$U$100) -> 579.8751 | ... AU100: =AT100*(1+$U$100) -> 474.66031
B101: Número de Lojas - Continuadas | C101: Number of Stores - Continued brands | D101: 781 | E101: 775 | F101: 770 | G101: 785 | H101: 764 | I101: 755 | J101: 745 | K101: 739 | L101: 720 | M101: 711 | N101: 704 | O101: 700 | P101: 685 | Q101: 671 | R101: 649
B102: Lojas Próprias | C102: Owned Stores | D102: 71 | E102: 71 | F102: 70 | G102: 70 | H102: 68 | I102: 68 | J102: 68 | K102: 68 | L102: 68 | M102: 68 | N102: 68 | O102: 67 | P102: 67 | Q102: 66 | R102: 59
B103: Hering | C103: Hering | D103: 62 | E103: 62 | F103: 61 | G103: 59 | H103: 57 | I103: 55 | J103: 53 | K103: 51 | L103: 51 | M103: 50 | N103: 49 | O103: 43 | P103: 43 | Q103: 42 | R103: 34
B104: Hering - Megalojas | C104: Hering - Megastores | D104: 9 | E104: 9 | F104: 9 | G104: 11 | H104: 11 | I104: 13 | J104: 15 | K104: 17 | L104: 17 | M104: 18 | N104: 19 | O104: 24 | P104: 24 | Q104: 24 | R104: 25
B105: Franquias | C105: Franchises | D105: 691 | E105: 685 | F105: 681 | G105: 696 | H105: 677 | I105: 668 | J105: 658 | K105: 652 | L105: 633 | M105: 624 | N105: 617 | O105: 613 | P105: 598 | Q105: 585 | R105: 569
B106: Hering | C106: Hering | D106: 686 | E106: 677 | F106: 673 | G106: 686 | H106: 666 | I106: 656 | J106: 644 | K106: 636 | L106: 615 | M106: 601 | N106: 593 | O106: 585 | P106: 568 | Q106: 553 | R106: 536
B107: Hering - Megalojas | C107: Hering - Megastores | D107: 5 | E107: 8 | F107: 8 | G107: 10 | H107: 11 | I107: 12 | J107: 14 | K107: 16 | L107: 18 | M107: 23 | N107: 24 | O107: 28 | P107: 30 | Q107: 32 | R107: 33
B108: Internacional | C108: Internacional | D108: 19 | E108: 19 | F108: 19 | G108: 19 | H108: 19 | I108: 19 | J108: 19 | K108: 19 | L108: 19 | M108: 19 | N108: 19 | O108: 20 | P108: 20 | Q108: 20 | R108: 21
B109: Número de Lojas - Descontinuadas | C109: Number of Stores - Discontinued brands | D109: 2 | E109: 2 | F109: 2 | G109: 3 | H109: 3 | I109: 3 | J109: 3 | K109: 3 | L109: 3 | M109: 3 | N109: 2 | O109: 2 | P109: 1 | Q109: 1 | R109: 0
...

Sheet Disclaimer
